{"letters":["&","0","1","2","4","6","7","8","A","B","C","D","E","G","H","I","J","L","M","N","O","P","R","S","T","U","W","X","Z","a","b","c","d","e","f","g","h","i","j","k","l","m","n","o","p","r","s","t","u","v","w","x","y","·","ʼ","ᵃ","ᵇ","ᶜ","₀","₁","₂","₃","₄","₅","₆","₇","₈","₉","⸼"],"markers":[" ",",",".",":",";","?","¶","—","⁺"],"words":{"0":[],"1":["10⸼","14⸼","17⸼"],"2":["22⸼","27⸼"],"4":["46⸼"],"6":["6⸼"],"7":["7⸼"],"8":["8⸼"],"&":["&c⸼"],"A":["Acts","And","Asher"],"B":["Because","Behold","Benjamin","Book","But"],"C":["CHAPTER","Come"],"D":["Dan","Deut⸼"],"E":["EXODUS","Egypt","Egyptian","Egyptians","Every"],"G":["Gad","Gen⸼","God"],"H":["Hebrew","Heb⸼"],"I":["Israel","Issachar","I⸼"],"J":["Jacob","Joseph","Josephʼs","Judah"],"L":["Levi"],"M":["Moses"],"N":["Naphtali","Now"],"O":[],"P":["Pharaoh","Pithom","Puah"],"R":["Raamses","Reuben"],"S":["Second","Shiphrah","Simeon"],"T":["The","Therefore"],"U":[],"W":["When","Why"],"X":[],"Z":["Zebulun"],"a":["a","abundantly","afflict","afflicted","after","against","alive","all","already","also","and","any","are","arose","as"],"b":["be","because","bitter","bondage","born","brethren","brick","built","burdens","but","by"],"c":["called","came","cast","chap⸼","charged","children","cities","come","commanded","commandeth"],"d":["daughter","deal","dealt","death","delivered","did","died","do","done"],"e":["enemies","ere","every","exceeding"],"f":["falleth","feared","field","fight","filled","for","fruitful"],"g":["generation","get","godliness","grew","grieved"],"h":["hard","have","he","him","his","household","houses"],"i":["if","in","increased","into","is","it"],"j":["join"],"k":["kill","king","knew"],"l":["land","lest","let","live","lively","lives","loins"],"m":["made","male","man","manner","men","midwife","midwives","mightier","mighty","more","morter","multiplied","multiply"],"n":["name","names","new","not"],"o":["of","office","on","one","oppressed","other","our","out","over"],"p":["pass","people"],"r":["rigour","river"],"s":["said","save","saved","saving","saying","see","serve","service","set","seventy","shall","she","so","son","souls","spake","stools"],"t":["taskmasters","than","that","the","their","them","then","there","these","they","thigh","thing","this","to","treasure"],"u":["unto","up","upon","us"],"v":["very"],"w":["war","was","waxed","we","well","were","when","wherein","which","wisely","with","women"],"x":[],"y":["ye"],"·":[],"ʼ":[],"ᵃ":["ᵃ"],"ᵇ":["ᵇ"],"ᶜ":["ᶜ"],"₀":[],"₁":["₁","₁₀","₁₁","₁₂","₁₃","₁₄","₁₅","₁₆","₁₇","₁₈","₁₉"],"₂":["₂","₂₀","₂₁","₂₂"],"₃":["₃"],"₄":["₄"],"₅":["₅"],"₆":["₆"],"₇":["₇"],"₈":["₈"],"₉":["₉"],"⸼":[]},"breaks":{"START":{" ":[],",":[],".":[],":":[],";":[],"?":[],"¶":[],"—":["————"],"⁺":["⁺ "]},"MIDDLE":{" ":[" "," ¶ "," ⁺"],",":[", "],".":[". "],":":[": "],";":["; "],"?":[],"¶":[],"—":[],"⁺":[]},"END":{" ":[],",":[","],".":["."],":":[":"],";":[],"?":["?"],"¶":[],"—":[],"⁺":[]}},"word_errors":["&c","1·","7","book","moses","second","·"],"break_errors":{"START":[],"MIDDLE":[],"END":[]}}