{"letters":["0","1","2","3","4","5","6","7","8","9","A","B","C","D","E","G","H","I","J","K","L","M","N","O","P","R","S","T","U","W","Y","a","b","c","d","e","f","g","h","i","j","k","l","m","n","o","p","r","s","t","u","v","w","y","z","ʼ","‑","⸼"],"markers":[" ","!","(",")",",",".",":",";","?","¶"],"words":{"0":[],"1":["1","10","11","12","13","14","15","16","17","18","19"],"2":["2","20","21","22","23","24","25","26","27","28","29"],"3":["3","30","31","32","33","34","35","36","37","38","39"],"4":["4","40","41","42","43","44","45","46"],"5":["5"],"6":["6"],"7":["7"],"8":["8"],"9":["9"],"A":["Abraham","After","Also","Amorites","Anakims","And","Astaroth"],"B":["Bashan","Because","Behold","But"],"C":["CHAPTER","Caleb","Canaanites"],"D":["DEUTERONOMY","Dizahab","Dread"],"E":["Edrei","Egypt","Eshcol","Euphrates"],"G":["Go","God","Godʼs"],"H":["Hazeroth","Hear","Heshbon","Horeb","Hormah","How"],"I":["I","Isaac","Israel","It","I⸼"],"J":["Jacob","Jephunneh","Jordan","Joshua"],"K":["Kadesh","Kadesh‑barnea"],"L":["Laban","Lebanon","Lord"],"M":["Moab","Moreover","Moses"],"N":["Notwithstanding","Nun"],"O":["Og","On"],"P":["Paran"],"R":["Red"],"S":["Save","Say","Seir","Sihon","So","Surely"],"T":["Take","The","Then","There","These","Thou","Tophel","Turn"],"U":[],"W":["We","Whither","Who"],"Y":["Ye","Yet"],"a":["a","able","abode","according","afraid","after","again","against","all","alone","also","am","among","and","angry","answered","are","as","at"],"b":["bare","be","bear","because","bees","before","began","behold","believe","between","bless","brethren","bring","brother","brought","burden","but","by"],"c":["came","can","captains","cause","causes","charged","chased","chief","children","cities","cloud","come","commanded","commandment","cumbrance"],"d":["day","days","daysʼ","declare","deliver","departed","destroy","destroyed","did","discouraged","do","doth","down","dwelt"],"e":["ear","eleven","eleventh","encourage","enemies","enough","even","every","evil","eyes"],"f":["face","fathers","fear","fifties","fight","fire","first","followed","for","forth","fortieth","from","fruit"],"g":["generation","girded","give","given","go","goeth","good","great","greater"],"h":["had","hand","hands","hard","hast","hated","hath","have","he","heads","hear","heard","hearken","heart","heaven","hill","hills","him","his","how","hundreds"],"i":["in","inherit","into","is","it"],"j":["journey","judge","judges","judgment"],"k":["king","knowledge","known"],"l":["land","law","lest","little","long"],"m":["made","make","man","many","me","men","month","more","moreover","mount","mountain","multiplied","multitude","murmured","must","myself"],"n":["near","neither","nigh","night","no","nor","not"],"o":["of","officers","on","one","ones","our","out","over"],"p":["pass","people","persons","pitch","place","places","plain","pleased","possess","presumptuously","prey","promised"],"r":["ready","rebelled","respect","returned","righteously","river","rulers"],"s":["said","sakes","saw","saying","sea","search","searched","see","seed","seen","send","set","shall","shalt","shew","should","side","sinned","slain","small","smitten","so","son","sons","south","spake","spoken","standeth","stars","stranger","strife","sware"],"t":["take","taller","tens","tents","terrible","than","that","the","thee","their","them","there","thereunto","these","they","thing","things","this","thither","thou","thousand","thousands","through","thy","time","times","to","too","took","tribe","tribes","trodden","turn","turned","twelve"],"u":["understanding","until","unto","up","upon","us"],"v":["vale","valley","voice"],"w":["walled","war","was","way","we","weapons","well","went","wept","were","what","when","where","which","wholly","wilderness","will","wise","with","word","words","would","wroth"],"y":["ye","year","you","your"],"z":[],"ʼ":[],"‑":[],"⸼":[]},"breaks":{"START":{" ":[],"!":[],"(":[],")":[],",":[],".":[],":":[],";":[],"?":[],"¶":[]},"MIDDLE":{" ":[" "," ("," ¶ "],"!":[],"(":[],")":[],",":[", "],".":[". "],":":[": "],";":["; "],"?":["? "],"¶":[]},"END":{" ":[],"!":["!)"],"(":[],")":[],",":[","],".":[".",".)"],":":[":"],";":[";"],"?":["?"],"¶":[]}},"word_errors":["bad"],"break_errors":{"START":[],"MIDDLE":[],"END":[]}}