{"letters":["0","1","2","3","4","5","6","7","8","9","A","B","C","D","E","F","G","H","I","J","L","M","N","O","P","Q","R","S","T","U","V","X","Z","a","b","c","d","e","f","g","h","i","j","l","m","n","o","p","q","r","s","t","u","v","x","y","z","Æ","æ","œ","̈","⸼"],"markers":[" ","(",")",",",".",":",";","?"],"words":{"0":[],"1":["1","10","11","12","13","14","15","16","17","18","19"],"2":["2","20","21","22","23","24","25","26","27","28","29"],"3":["3","30","31","32","33","34","35","36","37","38","39"],"4":["4","40","41","42","43","44","45","46","47","48","49"],"5":["5","50","51","52","53","54","55","56","57","58","59"],"6":["6","60","61","62","63","64","65","66","67","68","69"],"7":["7","70","71","72","73","74","75","76","77","78","79"],"8":["8","80","81","82","83","84","85","86","87","88","89"],"9":["9"],"A":["A","Aaron","Abidan","Abihaiel","Abiu","Ac","Accipies","Acetabulum","Acetum","Achiman","Ad","Adducet","Adhuc","Adjurabitque","Ahiezer","Ahira","Ait","Alii","Amalec","Amen","Aminadab","Amisaddai","Ammiel","Ammisaddai","Ammiud","Amorrhæus","Amram","Amramitas","Anima","Anno","Applica","Arietem","Ascendamus","Ascenderuntque","Ascendite","Aser","Aspergantur","Assumetque","At","Audite","Audivit"],"B":["Benedicat","Benjamin","Bovem","Boves"],"C":["CAPUT","Caath","Caathitarum","Caathitæ","Cades","Caleb","Canistrum","Castrametabuntur","Castrametati","Chanaan","Chananæus","Circuibatque","Clamavitque","Cognatio","Columnas","Columnæque","Confitebuntur","Confortamini","Congrega","Considerate","Convertat","Cortinas","Cui","Cum","Cumque","Cuncta","Cunctis","Cunctus","Cunctusque","Cur"],"D":["Da","Dabisque","Dabo","Dan","De","Dei","Deo","Depositumque","Descendit","Descenditque","Det","Detraxeruntque","Deus","Die","Dixerunt","Dixit","Dixitque","Domine","Domini","Domino","Dominum","Dominus","Dormierit","Duel","Duo"],"E":["Ecce","Ego","Egredimini","Egressi","Eldad","Eleazar","Elevavitque","Eliab","Eliasaph","Elisama","Elisaphan","Elisur","Emath","Enac","Enan","Ephraim","Ephraïm","Erat","Erunt","Eruntque","Et","Ex","Exclusa","Extendentque","Externus"],"F":["Fac","Faciant","Facietque","Factum","Fecerunt","Feceruntque","Fecit","Fecitque","Filii","Filiis","Filiorum","Filios","Fuerunt","Fueruntque"],"G":["Gad","Gaddi","Gamaliel","Geddiel","Gedeonis","Gemalli","Gerson","Gersonitarum","Guel"],"H":["Haseroth","Hebron","Hebronitas","Helisur","Helon","Hethæus","Hi","Hic","Hircumque","His","Hobab","Hoc","Homo","Humus","Huri","Hæ","Hæc"],"I":["III⸼","II⸼","IV⸼","IX⸼","Ibi","Ibique","Igal","Igitur","Immundi","In","Incensio","Ingrediantur","Ingredientur","Inter","Interea","Invocabuntque","Ipsa","Ipsi","Ipsum","Iratusque","Israel","Israeli","Israelis","Israël","Issachar","Ista","Ita","Itaque","Ithamar","I⸼"],"J":["Jam","Jebusæus","Jephone","Jesaar","Jesaaritas","Jordanis","Joseph","Josue","Jubente","Juda","Judas","Judæ","Juxta"],"L":["Lael","Lebni","Lebnitica","Levabitur","Levi","Levitarum","Levitas","Levitis","Levitæ","Locutaque","Locutique","Locutus","Locutusque","Loquere"],"M":["Machi","Madianitæ","Man","Manasse","Maria","Mariam","Maritus","Maritusque","Mea","Medad","Mensam","Merari","Meraritarum","Metabuntur","Meum","Michael","Misit","Mitte","Moholi","Moholitæ","Mortariola","Mortariolum","Mortui","Moverunt","Moveruntque","Moyse","Moysen","Moyses","Moysi","Munera","Musi","Musitæ"],"N":["NUMERI","Nadab","Nahabi","Nahasson","Nathanael","Ne","Nec","Nehelescol","Nephthali","Nequaquam","Noli","Nolite","Non","Novissimi","Nubes","Num","Numera","Numerati","Numeratique","Numeravit","Numquid","Nun"],"O":["Obsecro","Obtulerunt","Obtulit","Ochran","Offeret","Omnes","Omni","Omnia","Omnibus","Omnis","Ore","Osee","Ostendat","Oziel","Ozielitas"],"P":["Per","Peregrinus","Pergentesque","Phadassur","Phalti","Pharan","Phase","Phegiel","Phegiël","Ponentque","Populo","Porro","Porta","Portabunt","Primo","Princeps","Princepsque","Pro","Profecti","Profectique","Profectusque","Proficiscimur","Præcepitque","Præceptum","Præcipe","Pugillum","Purificatique"],"Q":["Quadraginta","Quando","Quare","Quartadecima","Quarum","Quas","Quatuor","Qui","Quibus","Quid","Quinquaginta","Quis","Quod","Quorum","Quos","Quot","Quæ"],"R":["Raguel","Raphu","Recensiti","Recensuerunt","Recensuit","Recordamur","Remanserant","Reversique","Reversusque","Revertere","Rohob","Ruben"],"S":["Salamiel","Salamiël","Sammua","Sancta","Sanctificamini","Sanctum","Sanctus","Saphat","Scribetque","Secundo","Sed","Sedeur","Semei","Semeitica","Separetur","Sepulchra","Sepulchris","Sexaginta","Sexcenta","Si","Sic","Siclus","Sicque","Sicut","Simeon","Sin","Sinai","Singuli","Sisai","Sodi","Spiritum","Spiritus","State","Statim","Statuesque","Sthur","Stirpem","Suar","Sub","Sument","Super","Surge","Surgens","Suriel","Surisaddai","Susceptaque","Suscipe","Susi"],"T":["Tabernaculum","Tam","Tamdiu","Tanim","Terra","Tertio","Tholmai","Tolle","Tollent","Tollesque","Tollet","Tollite","Torrens","Torrentem","Tradidique","Tribum","Triginta","Tulit","Tunc"],"U":["Unde","Universi","Unum","Ut"],"V":["VIII⸼","VII⸼","VI⸼","Vapsi","Venerunt","Venimus","Venit","Ventus","Vir","Vocatusque","Vocavitque","Vulgus","V⸼"],"X":["XIII⸼","XII⸼","XI⸼","X⸼"],"Z":["Zabulon","Zechur"],"a":["a","ab","abiit","ablata","abortivum","absciderunt","absorptus","absque","abstinebunt","ac","accedentes","accedere","accensus","accepi","accesserit","accidere","accipient","accipies","acetabula","acetabulum","acinum","ad","adducet","adduxerit","adulterii","adulterium","advena","advenæ","adversum","aere","afferte","afficiar","afflixisti","agni","agnos","agnum","agrestibus","aiebat","ait","alia","alienum","alienus","alioquin","aliter","aliud","allia","altare","altaria","altaris","alter","altero","alterum","altitudine","amarissimas","amarissimis","amarissimæ","amen","amplius","an","anima","anniculam","anniculi","anniculos","anniculum","annis","anno","annos","annum","annumerati","ante","aperit","aperiunt","apparebo","apparuit","appellatus","appendens","appendentia","appenditur","appetitur","applicabis","apud","aqua","aquam","aquas","aquilonis","aquis","aquæ","arboribus","arca","arcam","arcaque","argentea","argenteam","argenteas","argenteum","argenteæ","argenti","argento","argui","arida","ariete","arietem","arietes","arietis","armentis","armento","armum","arreptans","ascenderat","ascendere","ascendissent","aspeximus","at","atque","atrii","audiebat","audisset","audivi","auferam","auferens","aurea","aureis","aureum","auri","auro","ausi","australi","aut","autem","azymis","azymorum","azymum"],"b":["bases","basibus","batilla","bdellii","bella","bellum","bene","benedicam","benedicetis","benefaciamus","bibent","bibere","biberit","biduo","bobus","bona","boream","botri","botrum","boum","bovem","boves"],"c":["calamorum","calendas","candelabri","candelabrum","candens","canetis","canistro","canistrum","capillos","capita","capitis","capitum","caput","carnes","carnis","carnium","castra","castrametabantur","castrametabuntur","castrametandum","castrametati","castris","castrorum","centum","ceremonias","cessabunt","cessaverunt","cherubim","cibum","cibus","cinere","circa","circuita","circuitum","clamasset","clangent","clangetis","clangor","clangueris","coccineum","coctum","cognationes","cognationibus","cognationum","cognato","cognosci","colligens","coloris","columbæ","columna","columnas","columnæ","comedamus","comedatis","comedebamus","comedent","comedetis","commendata","commisimus","commotione","commune","comparati","compescens","compleatur","complebuntur","completum","complevit","compositionis","computrescet","concepi","concinnandas","concise","concisus","concitatus","concitaverit","concubuisti","concupiscentiæ","condita","confici","confringent","congessi","congessit","congregabitur","congregabuntur","congregandus","congregans","congregationis","congregaverunt","congregavit","consecrabis","consecrabit","consecrantur","consecrare","consecratio","consecrationis","consecratum","consecratur","consecratæ","considerandam","considerent","conspectu","conspersa","conspersam","conspersi","constitue","constitues","consulam","consuleret","contaminabitur","contaminent","contemnens","contempto","contra","convocare","convocata","coquens","coram","coriandri","coros","cortinas","coturnices","coturnicum","cras","crateras","crescente","cubitis","cucumeres","cucurrit","cui","cujus","culpa","cultores","cultum","cultus","cum","cuncta","cunctamque","cunctis","cunctorum","cunctus","cuneos","cur","curam","curiositate","custodia","custodiam","custodiant","custodiat","custodient","custodiis","custodiæ","cyathos","cædetur","cæpe","cæsarie","cœtum"],"d":["dabimus","dabit","dabunt","dans","daturus","de","debeamus","debeant","debeat","debebunt","debentur","debuerat","decem","decimam","decimo","declinasti","declinaverit","decreverat","dedicatione","dedicationem","dedit","defecerat","defer","deinde","delebit","deliquerint","dem","demisit","denos","dentibus","deponebant","deponent","deponeretur","deponetur","deprecabitur","depreceris","deprehendere","descendam","descendebat","descenderet","descripti","deserto","desertum","desideraverat","desiderio","desuper","det","detrahere","detulit","devorat","devoratum","devoravit","devoverat","dicas","dicebant","dicebat","dicens","dicentes","dicere","dices","dicet","dicetis","die","diebus","diem","dierum","dies","diluculo","dimicant","discooperiet","disponent","dispones","disrumpatur","dissipabant","dissipentur","divident","divisi","dixerunt","dixit","dolentium","domine","domo","domorum","domos","donati","donec","dono","dormivit","duas","ducenti","ducentorum","duces","ductiles","ductili","ductor","duntaxat","duo","duobus","duodecim","duodecimo","duos","dux","duæ"],"e":["e","ea","eadem","eam","earum","eas","ecce","ego","egrediebantur","egrediens","egredientur","egressi","egressionis","ei","eis","ejecerunt","ejiciant","ejicite","ejus","electus","elevabit","elevaretur","elevata","emunctoriis","enim","eo","eodem","eorum","eos","epulum","erant","erantque","erat","erectionis","erectum","erexit","ergo","erigatur","erigebant","erigent","erigetur","eris","erit","eritque","erraverit","eruamini","erunt","eruntque","es","escas","esse","est","esum","et","etiam","eum","evenisset","ex","excedunt","exceptis","excepto","excubabunt","excubent","excubias","excubiis","excubitores","exeat","execratione","exemplum","exemplumque","exercitu","exercitum","exercitus","exhauserit","exierant","exieritis","expiatione","explendos","exploratores","exploraverunt","exprimitur","extendent","extendentque","exterminabitur","externorum","extra","extremam"],"f":["fac","facere","facerent","faciant","faciat","facie","faciem","faciens","facient","facies","faciesque","faciet","facite","factum","factura","falsa","familiarum","familias","familiæ","farinæ","fecerint","fecerit","fecerunt","fecit","feminam","femur","fermento","festos","fiant","fiat","ficis","fictili","fidelissimus","fiebat","figebant","figent","figet","figuras","filii","filiis","filio","filiorum","filios","filium","filius","fixere","fixis","flagravit","flens","flent","flentem","fleveritis","fluenta","fluit","forcipibus","fores","fortior","fortis","fortissimos","fortium","frangebat","fratris","fratrum","fraudamur","fructibus","fructus","fuerant","fuere","fuerint","fuerit","fuerunt","fugiant","fuissent","fuisset","fuit","functique","fundenda","fundet","funere","funes","fungerentur","funibus","funiculos","furor","fuscinulas","fœderis"],"g":["generationes","generationibus","genere","generis","gente","genui","giganteo","granatis","grandes","gratiam","gratis","graveris","gravis","gyrum"],"h":["habebant","habebis","habebit","habebitis","habebunt","habens","habentem","habentes","haberet","habet","habitant","habitat","habitator","habitatores","habitaverim","hanc","hirci","hircos","his","hoc","holocaustis","holocaustum","homine","homines","hominibus","hominis","hordeaceæ","hos","hostes","hostia","hostiam","hostias","hujus","hujuscemodi","humeris","hunc","hyacinthino","hyacinthinum","hæc"],"i":["ianthinarum","ianthinum","ibi","id","idem","igitur","ignem","ignis","ignium","iissent","illa","ille","illico","illius","illo","illud","illum","immaculatam","immaculatum","immolabit","immundi","immundus","imperaverat","imperium","impleverint","imponas","imponet","imponetque","imposuisti","imposuit","in","incederent","incendat","incenso","incensum","incensus","increpueris","increpuerit","inde","indigenæ","indignatio","inducent","inducentque","inebriare","infantulum","infirmus","inflato","ingrederentur","ingrederetur","ingredientes","ingredientur","ingredietur","ingrediuntur","inimici","inimicorum","iniquitatem","innoxia","inquit","inspexerant","integro","inter","interficias","intoleranda","intrabunt","intrant","intrantibus","introitu","invalida","invenerit","inveniam","invenio","inventa","inventi","investigans","involuta","involvantur","involvent","involventque","involverint","ipsa","ipse","ipsi","ipsique","ipsius","ipsum","iratus","irriti","ista","istæ","ita","itaque","itinere"],"j":["jam","jugiter","jumentis","junctis","jurasti","jussum","justificationes","juxta"],"l":["labore","lacte","lactucis","lagana","laganum","latere","latet","laverint","laverunt","legitimum","lepra","leprosum","levabunt","lex","liba","libamenta","libamentum","libamina","libello","liberis","liberos","loca","loci","locis","loco","locum","locus","locustæ","locutus","longiori","loquar","loquebatur","loquentis","loquor","lucere","lucernas","lucernis","lucernæ","lustrationis","lustravimus"],"m":["magistri","magna","majores","mala","maledicta","maledictionem","maledictionibus","maledictionis","maledictæ","malis","mancipari","mandatum","mandaverat","mane","manebant","maneret","manibus","manserunt","manu","manum","manus","mare","maris","mariti","maritumque","maritus","masculi","masculim","masculini","masculino","masculum","matris","me","mea","meam","medio","medium","medius","mei","melle","mensam","mensamque","mense","mensem","mensis","mensuram","mente","mentem","meo","meos","meridianam","meridie","meridiem","metabuntur","meum","meus","mi","mihi","mille","millia","minister","ministerii","ministerio","ministerium","ministrandum","ministrant","ministratur","ministrent","ministri","misereatur","misisti","misit","mitissimus","mittens","mittet","modum","mola","monstra","montanis","monte","montes","morabantur","moratur","more","moriantur","morientur","morietur","mortario","mortariola","mortariolum","mortua","mortuo","mortuum","mortuus","motus","movebant","movebunt","movenda","mulier","mulieri","multitudine","multitudinem","multitudini","multitudinis","multitudo","multo","mundabunt","mundati","mundus","munera","munus","muratas","muratæ","muris","murmur"],"n":["nam","nares","narraverunt","narravit","nascebantur","nascitur","natu","natus","nauseam","nazaræi","nazaræus","ne","nec","necessaria","necessarium","negligentiam","nemorosa","neque","nihil","nimis","nisi","nix","nobilissimi","nobis","nobiscum","nocebunt","nocte","noctem","noli","nomen","nomina","nominibus","non","nonne","nos","noster","nosti","nostra","nostri","novacula","novem","novissimi","nubem","nubes","nubis","nulla","numerabitis","numerare","numerati","numeratus","numeraverunt","numeravit","numero","numerum","numerus","nunc","nuntiavit","nutrix"],"o":["oblata","oblatio","oblationem","oblatos","obolos","obsecro","observabunt","observent","obtinere","obtulere","obtulerunt","obtuleruntque","obtulit","occidentalem","occidentem","occidetur","octava","octavo","octo","octoginta","oculi","oculis","oderunt","offerant","offerens","offeret","offerre","offerrent","offertur","offerunt","officia","officium","oleati","olei","oleo","oleum","olla","omne","omnem","omnes","omni","omnia","omnibus","omnis","omnium","omniumque","onera","oneri","onus","opera","operatus","opere","operiebat","operient","operimentum","operuit","opibus","optimum","oraculum","oravit","ordinem","ordines","orent","oriebatur","orientalem","orientem","ortum","os","ostenderunt","ostendit","ostia","ostium","ovem","ovium"],"p":["pacem","pacificam","pacificis","pacificorum","palam","pallio","pallium","palmitem","panes","panis","panum","pari","pariter","parte","partem","parum","passa","pater","patre","patribus","patris","patrum","pauci","pauxillum","pavimento","paxilli","paxillis","peccatis","peccato","peccatum","peccaverint","peccavit","pecora","pecoribus","pecorum","pectusculum","pecuniam","pecus","peditum","pellium","pendet","pepones","per","percussi","percussit","perdere","perfectionem","perfusam","pertinent","pertinet","pertransibunt","phiala","phialam","phialæ","pilos","pinguis","pisces","piscium","placabilis","plaga","plagam","plaustra","plaustrum","plena","plenum","plures","pluribus","polluetur","polluta","pollutusque","pondere","pondo","pondus","ponent","ponere","pones","ponet","populi","populis","populo","populos","populum","populus","porrique","portabatur","portabit","portabunt","portanda","portant","portantes","portare","portassent","portaverunt","portent","possideamus","possis","possit","possum","possunt","post","postea","postquam","posueris","poterant","poterimus","potest","potione","potum","pretio","pretium","prima","primi","primitiæ","primo","primogenita","primogenitis","primogenito","primogenitos","primogenitum","primogenitus","primum","princeps","principe","principes","principibus","principum","priores","prius","priusquam","pro","procedentium","procedere","procederent","proceræ","procul","profecti","profectionem","profectiones","proficiscebantur","proficiscendum","proficiscentur","prohibe","projicitur","prolixior","promiscuum","promisit","propheta","prophetant","prophetarent","prophetaverunt","prophetet","propitiatorio","propositionis","propriis","propter","protegebat","providens","præcedebat","præceperat","præceptum","præcipe","præcipiat","præcoquæ","præfectique","puer","pugnantium","pugnatorum","pullos","purgationis","purificabis","purificati","purpureo","putrescat","putrescere"],"q":["qua","quadraginta","quadringenti","quales","qualibet","qualis","quam","quando","quantum","quare","quartadecima","quarto","quas","quasi","quatuor","que","quem","qui","quia","quibus","quid","quidam","quidem","quidquid","quingenti","quinquagesimum","quinquaginta","quinque","quintamque","quinto","quippe","quippiam","quis","quispiam","quisquis","quiverit","quo","quod","quomodo","quoniam","quoque","quorum","quos","quæ","quædam"],"r":["radant","radet","radetur","rasum","rea","recensebis","recensentes","recenseri","recensiti","recensitæ","recensuerunt","recensuit","recentes","receptacula","recessisset","recessit","recipiat","recipiet","recordatio","recordationem","recordationis","recubuit","reddent","redemerant","regione","relinquent","relinquere","reliqui","reliquisset","repletæ","repuleritis","requievisset","requievit","res","respexisset","respiciant","respicit","respiciunt","respondebit","respondit","revera","revertar","revocabitur","revocata","ritum","ritus","ros","rubore","rursum"],"s":["sacerdos","sacerdotem","sacerdotes","sacerdoti","sacerdotii","sacerdotio","sacerdotis","sacerdotum","sacrificii","sacrificio","sacrificium","saltem","sana","sanctam","sanctificabitque","sanctificata","sanctificatio","sanctificationis","sanctificavi","sanctificavit","sanctificentur","sanctorum","sanctuarii","sanctuario","sanctuarium","sanctus","saporis","sati","satient","sceptri","scient","scripta","se","secundi","secundo","secundum","sed","sedens","semel","semen","semine","semper","sempiternum","senes","senibus","separabis","separari","separationis","sepelierunt","septem","septentrionali","septima","septimo","septingenti","septuaginta","sermo","sermonem","sermones","serviant","servientes","servire","serviunt","servo","servum","servus","sex","sexaginta","sexcenta","sexcenti","sexto","sexus","si","sibi","sic","siccasque","siccaverunt","sicli","siclis","siclorum","siclos","sicque","sicut","signa","simila","similam","similiter","simplex","simul","singula","singulas","singuli","singulis","singulorum","singulos","sint","sinu","sit","sive","solent","solet","solitudine","solum","solus","somnium","sonitu","sororisque","species","spiritu","spiritus","spuisset","stabat","stare","statim","statuet","staturæ","stent","sterilis","steterit","stetisset","stetit","stipes","stirpe","stulte","stupro","sua","suam","suarum","suas","sub","subito","subjacebis","sufficere","suffundi","sui","suis","sum","summa","summam","sumus","sunt","suo","suorum","suos","supellectilem","super","suppositus","supra","suscepisset","suspicione","sustentent","sustinere","suum","suæ","synagogæ"],"t":["tabernaculi","tabernaculo","tabernaculum","tabulas","tabulæ","talis","tam","tamen","tangent","tantis","tantum","tantæ","te","tecta","tecti","tectum","tecum","tempore","tempus","tenebit","tentoria","tentorii","tentoriis","tentorium","tentoriumque","terebat","terra","terram","terræ","tertii","testibus","testimonii","tetigerint","thoro","thuribula","thus","tibi","timuistis","tollat","tolletque","tortamque","tortulas","toto","totum","tradamque","trades","tradet","tradidit","traditi","traditur","traditurus","trahitur","trans","transgressi","transibit","trecenti","trecentorum","tres","tria","tribu","tribuat","tribubus","tribum","tribus","tribuum","tridentes","trigesimo","triginta","trium","tu","tua","tubarum","tubas","tubis","tubæ","tui","tuis","tulerunt","tuli","tumens","tumescente","tunc","tuo","turba","turmas","turtures","tuum","tuus"],"u":["ubi","ultra","ululabunt","ululantibus","ululatu","una","unam","uncinos","uncta","uncti","unctionis","unctum","unde","undecimo","universi","universis","universæ","uno","unum","unumquemque","unus","unusquisque","unxitque","urbem","urbes","usque","ut","utensilia","utero","uterus","utroque","utrum","utrumque","utuntur","uva","uvas","uvæ","uxor","uxorem"],"v":["vadam","valde","valeamus","valemus","vasa","vase","vasis","vasorum","vecte","vectes","vel","velamen","velamento","velamine","velum","veneris","veneritis","venerunt","veni","venient","venirent","veniunt","ventre","ventrem","verba","verbum","vero","vertatur","vescendum","vesci","vesperam","vespere","vester","vestimenta","vestimento","vestra","vestras","vestri","vestris","vestro","vestrorum","vexilla","via","viam","victimis","videant","videbamur","videbis","videt","videtur","vidimus","vidisset","vigesima","vigesimo","viginti","vinea","vino","vinum","vir","viri","viris","viro","virorum","viros","virum","visa","visione","vivant","vobis","vobiscum","vocabatur","vocans","vocavitque","vocem","volabantque","voluerint","vos","voto","votum","voverit","vulgi","vultum","vulva","vulvam"],"x":[],"y":[],"z":["zelotypiæ"],"Æ":["Ægypti","Ægypto","Æthiopissam"],"æ":["æmularis","ænigmata","ætatis"],"œ":[],"̈":[],"⸼":[]},"breaks":{"START":{" ":[],"(":[],")":[],",":[],".":[],":":[],";":[],"?":[]},"MIDDLE":{" ":[" "," ("],"(":[],")":[],",":[", "],".":[". "],":":[": "],";":["; "],"?":["? "]},"END":{" ":[],"(":[],")":[")"],",":[","],".":["."],":":[":"],";":[";"],"?":["?"]}},"word_errors":["11⸼","Egypto"],"break_errors":{"START":[],"MIDDLE":[],"END":[]}}