{"letters":["0","1","2","3","4","5","6","7","8","9","A","B","C","E","H","I","L","M","P","R","S","T","U","V","a","b","c","d","e","f","g","h","i","k","l","m","n","o","p","r","s","t","u","v","w","y","ʼ","⸼"],"markers":[" ",",",".",":",";","¶"],"words":{"0":[],"1":["1","10","11","12","13","14","15","16","17"],"2":["2"],"3":["3"],"4":["4"],"5":["5"],"6":["6"],"7":["7"],"8":["8"],"9":["9"],"A":["Aaron","Aaronʼs","And"],"B":["But"],"C":["CHAPTER"],"E":[],"H":[],"I":["If","Israel","I⸼"],"L":["LEVITICUS","Lord"],"M":["Moses"],"P":[],"R":[],"S":["Speak"],"T":[],"U":[],"V":[],"a":["a","about","accepted","all","altar","an","and","any","ashes","asunder","at","atonement","away"],"b":["be","before","beside","blemish","blood","bring","bullock","burn","burnt","but","by"],"c":["called","cast","cattle","children","cleave","congregation","crop","cut"],"d":["divide","door"],"e":["east","even"],"f":["fat","feathers","fire","flay","flock","flocks","for","fowls"],"g":["goats"],"h":["hand","he","head","herd","him","his"],"i":["if","in","into","inwards","is","it"],"k":["kill"],"l":["lay","legs","let"],"m":["made","make","male","man"],"n":["namely","northward","not"],"o":["of","off","offer","offering","on","or","order","out","own"],"p":["part","parts","pieces","pigeons","place","pluck","priest","priests","put"],"r":["round"],"s":["sacrifice","savour","say","saying","shall","sheep","side","sons","spake","sprinkle","sweet"],"t":["tabernacle","that","the","them","then","thereof","to","turtledoves"],"u":["unto","upon"],"v":["voluntary"],"w":["wash","water","which","will","wings","with","without","wood","wring","wrung"],"y":["ye","you","young","your"],"ʼ":[],"⸼":[]},"breaks":{"START":{" ":[],",":[],".":[],":":[],";":[],"¶":[]},"MIDDLE":{" ":[" "," ¶ "],",":[", "],".":[],":":[": "],";":["; "],"¶":[]},"END":{" ":[],",":[","],".":["."],":":[":"],";":[],"¶":[]}},"word_errors":[],"break_errors":{"START":[],"MIDDLE":[],"END":[]}}