{"unique_language_names":["English"],"total_unit_count":46493,"total_point_count":46493,"total_letter_count":30066,"total_marker_count":7956,"total_meta_letter_count":8471,"total_word_count":7215,"total_break_count":7212,"total_meta_word_count":1711,"total_part_count":16138,"total_line_count":269,"total_file_count":6,"language_unit_counts":{"English":46493},"language_point_counts":{"English":46493},"language_letter_counts":{"English":30066},"language_marker_counts":{"English":7956},"language_meta_letter_counts":{"English":8471},"language_word_counts":{"English":7215},"language_break_counts":{"English":7212},"language_meta_word_counts":{"English":1711},"language_part_counts":{"English":16138},"language_line_counts":{"English":269},"language_file_counts":{"English":6},"buffer_counts":{"0":6,"a":269,"A":[{"0":6,"b":6,"B":[{"0":6,"c":6,"C":[{"0":6,"d":15,"E":[{"0":6,"e":23},{"0":6,"e":11},{"0":1,"e":6},{"0":1,"e":2},{"0":1,"e":7}]}],"D":[{"0":6,"d":15,"E":[{"0":6,"e":57},{"0":6,"e":31},{"0":1,"e":12},{"0":1,"e":3},{"0":1,"e":15}]}]}]},{"0":6,"b":6,"B":[{"0":6,"c":6,"C":[{"0":6,"d":177,"E":[{"0":6,"e":36},{"0":5,"e":10},{"0":5,"e":10},{"0":5,"e":10},{"0":5,"e":11},{"0":5,"e":13},{"0":5,"e":12},{"0":5,"e":12},{"0":4,"e":10},{"0":4,"e":12},{"0":4,"e":8},{"0":4,"e":8},{"0":4,"e":10},{"0":3,"e":6},{"0":3,"e":7},{"0":3,"e":6},{"0":3,"e":7},{"0":3,"e":8},{"0":3,"e":7},{"0":3,"e":8},{"0":3,"e":6},{"0":3,"e":8},{"0":2,"e":5},{"0":2,"e":7},{"0":2,"e":6},{"0":2,"e":4},{"0":2,"e":4},{"0":2,"e":5},{"0":2,"e":6},{"0":2,"e":4},{"0":2,"e":4},{"0":2,"e":5},{"0":2,"e":6},{"0":2,"e":5},{"0":2,"e":7},{"0":2,"e":5},{"0":2,"e":4},{"0":2,"e":4},{"0":2,"e":4},{"0":2,"e":5},{"0":2,"e":7},{"0":2,"e":6},{"0":2,"e":4},{"0":2,"e":4},{"0":2,"e":6},{"0":2,"e":6},{"0":2,"e":9},{"0":2,"e":4},{"0":2,"e":4},{"0":2,"e":5},{"0":2,"e":6},{"0":2,"e":5},{"0":2,"e":6},{"0":2,"e":4},{"0":2,"e":4},{"0":2,"e":5},{"0":2,"e":6},{"0":2,"e":4},{"0":2,"e":5},{"0":2,"e":6},{"0":2,"e":6},{"0":1,"e":2},{"0":1,"e":2},{"0":1,"e":2},{"0":1,"e":2},{"0":1,"e":2},{"0":1,"e":3},{"0":1,"e":8},{"0":1,"e":2},{"0":1,"e":2},{"0":1,"e":2},{"0":1,"e":4}]}],"D":[{"0":6,"d":177,"E":[{"0":6,"e":43},{"0":5,"e":22},{"0":5,"e":24},{"0":5,"e":18},{"0":5,"e":31},{"0":5,"e":25},{"0":5,"e":22},{"0":5,"e":33},{"0":4,"e":24},{"0":4,"e":17},{"0":4,"e":28},{"0":4,"e":20},{"0":4,"e":23},{"0":3,"e":11},{"0":3,"e":21},{"0":3,"e":16},{"0":3,"e":19},{"0":3,"e":17},{"0":3,"e":21},{"0":3,"e":17},{"0":3,"e":16},{"0":3,"e":18},{"0":2,"e":16},{"0":2,"e":16},{"0":2,"e":9},{"0":2,"e":11},{"0":2,"e":11},{"0":2,"e":13},{"0":2,"e":14},{"0":2,"e":7},{"0":2,"e":13},{"0":2,"e":13},{"0":2,"e":9},{"0":2,"e":13},{"0":2,"e":15},{"0":2,"e":12},{"0":2,"e":13},{"0":2,"e":10},{"0":2,"e":7},{"0":2,"e":17},{"0":2,"e":18},{"0":2,"e":9},{"0":2,"e":12},{"0":2,"e":7},{"0":2,"e":17},{"0":2,"e":14},{"0":2,"e":11},{"0":2,"e":7},{"0":2,"e":11},{"0":2,"e":14},{"0":2,"e":9},{"0":2,"e":16},{"0":2,"e":11},{"0":2,"e":7},{"0":2,"e":11},{"0":2,"e":16},{"0":2,"e":11},{"0":2,"e":8},{"0":2,"e":10},{"0":2,"e":9},{"0":2,"e":16},{"0":1,"e":10},{"0":1,"e":4},{"0":1,"e":6},{"0":1,"e":3},{"0":1,"e":4},{"0":1,"e":9},{"0":1,"e":11},{"0":1,"e":4},{"0":1,"e":9},{"0":1,"e":4},{"0":1,"e":11}]}]}]},{"0":6,"b":6,"B":[{"0":6,"c":6,"C":[{"0":6,"d":1,"E":[{"0":1,"e":5}]}],"D":[{"0":6,"d":1,"E":[{"0":1,"e":11}]}]}]},{"0":6,"b":11,"B":[{"0":6,"c":6,"C":[{"0":6,"d":61,"E":[{"0":6,"e":22},{"0":5,"e":20},{"0":5,"e":10},{"0":5,"e":20},{"0":5,"e":10},{"0":5,"e":10},{"0":5,"e":12},{"0":5,"e":10},{"0":3,"e":6},{"0":3,"e":8},{"0":3,"e":6},{"0":1,"e":2},{"0":1,"e":2},{"0":1,"e":4},{"0":1,"e":2},{"0":1,"e":4},{"0":1,"e":2},{"0":1,"e":2},{"0":1,"e":2},{"0":1,"e":2},{"0":1,"e":2},{"0":1,"e":2}]}],"D":[{"0":6,"d":61,"E":[{"0":6,"e":25},{"0":5,"e":32},{"0":5,"e":21},{"0":5,"e":34},{"0":5,"e":28},{"0":5,"e":32},{"0":5,"e":29},{"0":5,"e":28},{"0":3,"e":14},{"0":3,"e":20},{"0":3,"e":17},{"0":1,"e":4},{"0":1,"e":4},{"0":1,"e":7},{"0":1,"e":4},{"0":1,"e":7},{"0":1,"e":6},{"0":1,"e":5},{"0":1,"e":6},{"0":1,"e":3},{"0":1,"e":6},{"0":1,"e":6}]}]},{"0":5,"c":5,"C":[{"0":5,"d":5,"E":[{"0":5,"e":5}]}],"D":[{"0":5,"d":5,"E":[{"0":5,"e":5}]}]}]},{"0":6,"b":11,"B":[{"0":6,"c":6,"C":[{"0":6,"d":140,"E":[{"0":5,"e":20},{"0":5,"e":10},{"0":5,"e":10},{"0":5,"e":12},{"0":5,"e":10},{"0":5,"e":11},{"0":5,"e":11},{"0":5,"e":10},{"0":5,"e":10},{"0":5,"e":10},{"0":5,"e":12},{"0":5,"e":10},{"0":5,"e":10},{"0":5,"e":15},{"0":5,"e":16},{"0":5,"e":11},{"0":5,"e":11},{"0":5,"e":15},{"0":5,"e":12},{"0":5,"e":10},{"0":4,"e":9},{"0":4,"e":11},{"0":4,"e":12},{"0":4,"e":9},{"0":3,"e":6},{"0":3,"e":7},{"0":3,"e":6},{"0":3,"e":6},{"0":3,"e":8},{"0":3,"e":6},{"0":3,"e":10},{"0":3,"e":8}]}],"D":[{"0":6,"d":140,"E":[{"0":5,"e":20},{"0":5,"e":29},{"0":5,"e":23},{"0":5,"e":26},{"0":5,"e":23},{"0":5,"e":30},{"0":5,"e":24},{"0":5,"e":23},{"0":5,"e":26},{"0":5,"e":23},{"0":5,"e":25},{"0":5,"e":23},{"0":5,"e":25},{"0":5,"e":29},{"0":5,"e":31},{"0":5,"e":27},{"0":5,"e":30},{"0":5,"e":40},{"0":5,"e":30},{"0":5,"e":29},{"0":4,"e":22},{"0":4,"e":15},{"0":4,"e":20},{"0":4,"e":24},{"0":3,"e":10},{"0":3,"e":31},{"0":3,"e":9},{"0":3,"e":21},{"0":3,"e":29},{"0":3,"e":15},{"0":3,"e":15},{"0":3,"e":18}]}]},{"0":5,"c":7,"C":[{"0":5,"d":18,"E":[{"0":5,"e":25},{"0":4,"e":9},{"0":4,"e":11},{"0":4,"e":10},{"0":1,"e":4}]},{"0":1,"d":4,"E":[{"0":1,"e":7},{"0":1,"e":2},{"0":1,"e":2},{"0":1,"e":1}]},{"0":1,"d":4,"E":[{"0":1,"e":7},{"0":1,"e":2},{"0":1,"e":2},{"0":1,"e":1}]}],"D":[{"0":5,"d":18,"E":[{"0":5,"e":25},{"0":4,"e":20},{"0":4,"e":20},{"0":4,"e":28},{"0":1,"e":12}]},{"0":1,"d":4,"E":[{"0":1,"e":7},{"0":1,"e":5},{"0":1,"e":4},{"0":1,"e":2}]},{"0":1,"d":4,"E":[{"0":1,"e":7},{"0":1,"e":5},{"0":1,"e":4},{"0":1,"e":2}]}]}]},{"0":6,"b":11,"B":[{"0":6,"c":6,"C":[{"0":6,"d":158,"E":[{"0":6,"e":23},{"0":6,"e":11},{"0":5,"e":12},{"0":5,"e":10},{"0":5,"e":12},{"0":5,"e":10},{"0":5,"e":10},{"0":5,"e":10},{"0":5,"e":11},{"0":5,"e":12},{"0":5,"e":10},{"0":5,"e":11},{"0":5,"e":10},{"0":5,"e":10},{"0":5,"e":11},{"0":5,"e":14},{"0":5,"e":11},{"0":5,"e":11},{"0":5,"e":10},{"0":5,"e":10},{"0":5,"e":10},{"0":5,"e":12},{"0":5,"e":10},{"0":5,"e":10},{"0":4,"e":8},{"0":4,"e":9},{"0":4,"e":8},{"0":4,"e":8},{"0":2,"e":4},{"0":2,"e":5},{"0":2,"e":4},{"0":2,"e":4},{"0":2,"e":5},{"0":2,"e":6},{"0":2,"e":4},{"0":2,"e":4},{"0":1,"e":2},{"0":1,"e":2},{"0":1,"e":2},{"0":1,"e":2}]}],"D":[{"0":6,"d":158,"E":[{"0":6,"e":29},{"0":6,"e":25},{"0":5,"e":27},{"0":5,"e":27},{"0":5,"e":32},{"0":5,"e":23},{"0":5,"e":26},{"0":5,"e":22},{"0":5,"e":28},{"0":5,"e":31},{"0":5,"e":22},{"0":5,"e":28},{"0":5,"e":28},{"0":5,"e":21},{"0":5,"e":31},{"0":5,"e":26},{"0":5,"e":27},{"0":5,"e":29},{"0":5,"e":25},{"0":5,"e":24},{"0":5,"e":23},{"0":5,"e":29},{"0":5,"e":29},{"0":5,"e":32},{"0":4,"e":26},{"0":4,"e":25},{"0":4,"e":14},{"0":4,"e":34},{"0":2,"e":7},{"0":2,"e":12},{"0":2,"e":7},{"0":2,"e":14},{"0":2,"e":13},{"0":2,"e":12},{"0":2,"e":11},{"0":2,"e":9},{"0":1,"e":4},{"0":1,"e":9},{"0":1,"e":3},{"0":1,"e":6}]}]},{"0":5,"c":5,"C":[{"0":5,"d":10,"E":[{"0":5,"e":9},{"0":1,"e":6},{"0":1,"e":7},{"0":1,"e":6},{"0":1,"e":2},{"0":1,"e":7}]}],"D":[{"0":5,"d":10,"E":[{"0":5,"e":9},{"0":1,"e":12},{"0":1,"e":15},{"0":1,"e":12},{"0":1,"e":3},{"0":1,"e":15}]}]}]},{"0":6,"b":11,"B":[{"0":6,"c":6,"C":[{"0":6,"d":168,"E":[{"0":6,"e":26},{"0":6,"e":16},{"0":6,"e":13},{"0":6,"e":14},{"0":6,"e":12},{"0":6,"e":12},{"0":6,"e":15},{"0":6,"e":14},{"0":6,"e":14},{"0":6,"e":15},{"0":6,"e":13},{"0":6,"e":14},{"0":6,"e":12},{"0":6,"e":13},{"0":6,"e":15},{"0":6,"e":12},{"0":6,"e":16},{"0":6,"e":20},{"0":6,"e":12},{"0":5,"e":11},{"0":5,"e":13},{"0":5,"e":10},{"0":4,"e":9},{"0":4,"e":8},{"0":4,"e":8},{"0":3,"e":6},{"0":3,"e":6},{"0":2,"e":5},{"0":2,"e":4},{"0":2,"e":4},{"0":2,"e":12},{"0":1,"e":2},{"0":1,"e":2},{"0":1,"e":2},{"0":1,"e":2},{"0":1,"e":2},{"0":1,"e":2},{"0":1,"e":2},{"0":1,"e":2},{"0":1,"e":2},{"0":1,"e":2},{"0":1,"e":2},{"0":1,"e":2},{"0":1,"e":2}]}],"D":[{"0":6,"d":168,"E":[{"0":6,"e":26},{"0":6,"e":27},{"0":6,"e":34},{"0":6,"e":36},{"0":6,"e":21},{"0":6,"e":38},{"0":6,"e":35},{"0":6,"e":34},{"0":6,"e":29},{"0":6,"e":26},{"0":6,"e":39},{"0":6,"e":27},{"0":6,"e":38},{"0":6,"e":40},{"0":6,"e":31},{"0":6,"e":31},{"0":6,"e":41},{"0":6,"e":36},{"0":6,"e":32},{"0":5,"e":25},{"0":5,"e":36},{"0":5,"e":22},{"0":4,"e":22},{"0":4,"e":16},{"0":4,"e":28},{"0":3,"e":11},{"0":3,"e":14},{"0":2,"e":18},{"0":2,"e":7},{"0":2,"e":12},{"0":2,"e":20},{"0":1,"e":8},{"0":1,"e":11},{"0":1,"e":3},{"0":1,"e":4},{"0":1,"e":9},{"0":1,"e":7},{"0":1,"e":3},{"0":1,"e":4},{"0":1,"e":6},{"0":1,"e":3},{"0":1,"e":6},{"0":1,"e":6},{"0":1,"e":7}]}]},{"0":5,"c":8,"C":[{"0":5,"d":10,"E":[{"0":5,"e":19},{"0":2,"e":9},{"0":2,"e":6},{"0":1,"e":5}]},{"0":2,"d":9,"E":[{"0":2,"e":12},{"0":2,"e":4},{"0":2,"e":8},{"0":1,"e":2},{"0":1,"e":2},{"0":1,"e":3}]},{"0":1,"d":4,"E":[{"0":1,"e":7},{"0":1,"e":2},{"0":1,"e":2},{"0":1,"e":1}]}],"D":[{"0":5,"d":10,"E":[{"0":5,"e":19},{"0":2,"e":16},{"0":2,"e":19},{"0":1,"e":7}]},{"0":2,"d":9,"E":[{"0":2,"e":20},{"0":2,"e":9},{"0":2,"e":14},{"0":1,"e":3},{"0":1,"e":4},{"0":1,"e":6}]},{"0":1,"d":4,"E":[{"0":1,"e":7},{"0":1,"e":7},{"0":1,"e":4},{"0":1,"e":2}]}]}]},{"0":6,"b":11,"B":[{"0":6,"c":6,"C":[{"0":6,"d":126,"E":[{"0":5,"e":20},{"0":5,"e":10},{"0":5,"e":10},{"0":5,"e":10},{"0":5,"e":14},{"0":5,"e":10},{"0":5,"e":10},{"0":5,"e":13},{"0":5,"e":10},{"0":3,"e":7},{"0":3,"e":8},{"0":3,"e":6},{"0":3,"e":6},{"0":3,"e":11},{"0":3,"e":7},{"0":3,"e":6},{"0":3,"e":6},{"0":3,"e":6},{"0":3,"e":7},{"0":3,"e":6},{"0":3,"e":6},{"0":3,"e":8},{"0":3,"e":7},{"0":3,"e":7},{"0":3,"e":6},{"0":3,"e":6},{"0":3,"e":6},{"0":3,"e":6},{"0":3,"e":6},{"0":2,"e":6},{"0":1,"e":2},{"0":1,"e":2},{"0":1,"e":5},{"0":1,"e":2},{"0":1,"e":2},{"0":1,"e":2},{"0":1,"e":3},{"0":1,"e":4},{"0":1,"e":2},{"0":1,"e":2},{"0":1,"e":2},{"0":1,"e":2},{"0":1,"e":2},{"0":1,"e":2},{"0":1,"e":2},{"0":1,"e":2},{"0":1,"e":2},{"0":1,"e":2},{"0":1,"e":2}]}],"D":[{"0":6,"d":126,"E":[{"0":5,"e":20},{"0":5,"e":14},{"0":5,"e":22},{"0":5,"e":23},{"0":5,"e":24},{"0":5,"e":27},{"0":5,"e":27},{"0":5,"e":31},{"0":5,"e":28},{"0":3,"e":24},{"0":3,"e":16},{"0":3,"e":14},{"0":3,"e":13},{"0":3,"e":15},{"0":3,"e":20},{"0":3,"e":14},{"0":3,"e":21},{"0":3,"e":13},{"0":3,"e":15},{"0":3,"e":13},{"0":3,"e":18},{"0":3,"e":18},{"0":3,"e":11},{"0":3,"e":25},{"0":3,"e":10},{"0":3,"e":12},{"0":3,"e":18},{"0":3,"e":16},{"0":3,"e":25},{"0":2,"e":13},{"0":1,"e":5},{"0":1,"e":4},{"0":1,"e":8},{"0":1,"e":3},{"0":1,"e":6},{"0":1,"e":3},{"0":1,"e":6},{"0":1,"e":6},{"0":1,"e":6},{"0":1,"e":4},{"0":1,"e":4},{"0":1,"e":6},{"0":1,"e":3},{"0":1,"e":4},{"0":1,"e":5},{"0":1,"e":3},{"0":1,"e":4},{"0":1,"e":5},{"0":1,"e":5}]}]},{"0":5,"c":6,"C":[{"0":5,"d":8,"E":[{"0":5,"e":11},{"0":1,"e":6},{"0":1,"e":2},{"0":1,"e":1}]},{"0":1,"d":4,"E":[{"0":1,"e":3},{"0":1,"e":2},{"0":1,"e":2},{"0":1,"e":1}]}],"D":[{"0":5,"d":8,"E":[{"0":5,"e":11},{"0":1,"e":13},{"0":1,"e":4},{"0":1,"e":2}]},{"0":1,"d":4,"E":[{"0":1,"e":3},{"0":1,"e":5},{"0":1,"e":3},{"0":1,"e":3}]}]}]},{"0":6,"b":12,"B":[{"0":6,"c":6,"C":[{"0":6,"d":156,"E":[{"0":6,"e":24},{"0":6,"e":14},{"0":6,"e":12},{"0":6,"e":15},{"0":6,"e":12},{"0":6,"e":12},{"0":6,"e":14},{"0":6,"e":18},{"0":6,"e":12},{"0":6,"e":14},{"0":6,"e":16},{"0":6,"e":13},{"0":6,"e":12},{"0":6,"e":13},{"0":6,"e":14},{"0":6,"e":12},{"0":6,"e":12},{"0":6,"e":13},{"0":4,"e":8},{"0":4,"e":10},{"0":3,"e":6},{"0":3,"e":8},{"0":3,"e":6},{"0":3,"e":6},{"0":3,"e":6},{"0":3,"e":7},{"0":3,"e":9},{"0":2,"e":4},{"0":2,"e":4},{"0":2,"e":4},{"0":2,"e":4},{"0":2,"e":4},{"0":1,"e":2},{"0":1,"e":2},{"0":1,"e":2},{"0":1,"e":2},{"0":1,"e":2},{"0":1,"e":2},{"0":1,"e":2},{"0":1,"e":3},{"0":1,"e":2}]}],"D":[{"0":6,"d":156,"E":[{"0":6,"e":24},{"0":6,"e":30},{"0":6,"e":27},{"0":6,"e":32},{"0":6,"e":35},{"0":6,"e":26},{"0":6,"e":45},{"0":6,"e":31},{"0":6,"e":40},{"0":6,"e":38},{"0":6,"e":32},{"0":6,"e":31},{"0":6,"e":30},{"0":6,"e":33},{"0":6,"e":40},{"0":6,"e":21},{"0":6,"e":28},{"0":6,"e":48},{"0":4,"e":15},{"0":4,"e":22},{"0":3,"e":13},{"0":3,"e":15},{"0":3,"e":9},{"0":3,"e":16},{"0":3,"e":19},{"0":3,"e":18},{"0":3,"e":19},{"0":2,"e":8},{"0":2,"e":12},{"0":2,"e":12},{"0":2,"e":9},{"0":2,"e":12},{"0":1,"e":5},{"0":1,"e":5},{"0":1,"e":4},{"0":1,"e":3},{"0":1,"e":4},{"0":1,"e":5},{"0":1,"e":3},{"0":1,"e":7},{"0":1,"e":7}]}]},{"0":6,"c":6,"C":[{"0":6,"d":9,"E":[{"0":6,"e":12},{"0":1,"e":2},{"0":1,"e":2},{"0":1,"e":5}]}],"D":[{"0":6,"d":9,"E":[{"0":6,"e":12},{"0":1,"e":5},{"0":1,"e":3},{"0":1,"e":7}]}]}]},{"0":6,"b":12,"B":[{"0":6,"c":6,"C":[{"0":6,"d":194,"E":[{"0":6,"e":24},{"0":6,"e":18},{"0":6,"e":12},{"0":6,"e":12},{"0":6,"e":16},{"0":6,"e":13},{"0":6,"e":13},{"0":6,"e":12},{"0":6,"e":12},{"0":6,"e":13},{"0":6,"e":13},{"0":6,"e":12},{"0":6,"e":13},{"0":6,"e":14},{"0":6,"e":14},{"0":6,"e":12},{"0":6,"e":13},{"0":6,"e":17},{"0":6,"e":12},{"0":6,"e":14},{"0":5,"e":11},{"0":5,"e":11},{"0":5,"e":11},{"0":5,"e":12},{"0":5,"e":10},{"0":5,"e":11},{"0":5,"e":13},{"0":4,"e":8},{"0":4,"e":12},{"0":4,"e":13},{"0":4,"e":11},{"0":4,"e":8},{"0":4,"e":10},{"0":4,"e":8},{"0":3,"e":8},{"0":2,"e":4},{"0":2,"e":4},{"0":2,"e":4},{"0":1,"e":2},{"0":1,"e":2}]}],"D":[{"0":6,"d":194,"E":[{"0":6,"e":24},{"0":6,"e":29},{"0":6,"e":30},{"0":6,"e":29},{"0":6,"e":31},{"0":6,"e":37},{"0":6,"e":30},{"0":6,"e":34},{"0":6,"e":26},{"0":6,"e":43},{"0":6,"e":25},{"0":6,"e":24},{"0":6,"e":35},{"0":6,"e":37},{"0":6,"e":44},{"0":6,"e":25},{"0":6,"e":43},{"0":6,"e":39},{"0":6,"e":23},{"0":6,"e":42},{"0":5,"e":31},{"0":5,"e":24},{"0":5,"e":27},{"0":5,"e":30},{"0":5,"e":25},{"0":5,"e":22},{"0":5,"e":42},{"0":4,"e":19},{"0":4,"e":22},{"0":4,"e":29},{"0":4,"e":23},{"0":4,"e":19},{"0":4,"e":16},{"0":4,"e":26},{"0":3,"e":18},{"0":2,"e":14},{"0":2,"e":8},{"0":2,"e":11},{"0":1,"e":5},{"0":1,"e":11}]}]},{"0":6,"c":7,"C":[{"0":6,"d":17,"E":[{"0":6,"e":28},{"0":4,"e":8},{"0":4,"e":10},{"0":3,"e":3}]},{"0":1,"d":5,"E":[{"0":1,"e":5},{"0":1,"e":3},{"0":1,"e":3},{"0":1,"e":2},{"0":1,"e":3}]}],"D":[{"0":6,"d":17,"E":[{"0":6,"e":28},{"0":4,"e":22},{"0":4,"e":24},{"0":3,"e":8}]},{"0":1,"d":5,"E":[{"0":1,"e":5},{"0":1,"e":4},{"0":1,"e":6},{"0":1,"e":4},{"0":1,"e":8}]}]}]},{"0":6,"b":12,"B":[{"0":6,"c":6,"C":[{"0":6,"d":154,"E":[{"0":6,"e":24},{"0":6,"e":12},{"0":6,"e":12},{"0":6,"e":13},{"0":6,"e":12},{"0":6,"e":12},{"0":6,"e":13},{"0":6,"e":12},{"0":6,"e":14},{"0":6,"e":13},{"0":6,"e":15},{"0":6,"e":12},{"0":6,"e":15},{"0":5,"e":11},{"0":5,"e":10},{"0":5,"e":10},{"0":5,"e":10},{"0":5,"e":11},{"0":4,"e":8},{"0":4,"e":8},{"0":4,"e":12},{"0":4,"e":11},{"0":4,"e":8},{"0":4,"e":8},{"0":4,"e":9},{"0":4,"e":8},{"0":4,"e":8},{"0":3,"e":6},{"0":2,"e":4},{"0":1,"e":2},{"0":1,"e":3},{"0":1,"e":2},{"0":1,"e":2},{"0":1,"e":2},{"0":1,"e":2},{"0":1,"e":2},{"0":1,"e":2},{"0":1,"e":2},{"0":1,"e":2}]}],"D":[{"0":6,"d":154,"E":[{"0":6,"e":24},{"0":6,"e":25},{"0":6,"e":28},{"0":6,"e":33},{"0":6,"e":27},{"0":6,"e":28},{"0":6,"e":36},{"0":6,"e":34},{"0":6,"e":31},{"0":6,"e":36},{"0":6,"e":41},{"0":6,"e":29},{"0":6,"e":30},{"0":5,"e":34},{"0":5,"e":25},{"0":5,"e":26},{"0":5,"e":20},{"0":5,"e":40},{"0":4,"e":17},{"0":4,"e":26},{"0":4,"e":24},{"0":4,"e":25},{"0":4,"e":19},{"0":4,"e":16},{"0":4,"e":18},{"0":4,"e":25},{"0":4,"e":21},{"0":3,"e":16},{"0":2,"e":14},{"0":1,"e":4},{"0":1,"e":11},{"0":1,"e":8},{"0":1,"e":3},{"0":1,"e":10},{"0":1,"e":6},{"0":1,"e":3},{"0":1,"e":5},{"0":1,"e":4},{"0":1,"e":4}]}]},{"0":6,"c":6,"C":[{"0":6,"d":6,"E":[{"0":6,"e":6}]}],"D":[{"0":6,"d":6,"E":[{"0":6,"e":6}]}]}]},{"0":6,"b":12,"B":[{"0":6,"c":6,"C":[{"0":6,"d":177,"E":[{"0":6,"e":24},{"0":6,"e":12},{"0":6,"e":12},{"0":6,"e":15},{"0":6,"e":12},{"0":6,"e":12},{"0":6,"e":12},{"0":6,"e":12},{"0":6,"e":13},{"0":6,"e":13},{"0":6,"e":14},{"0":6,"e":13},{"0":6,"e":17},{"0":6,"e":13},{"0":6,"e":14},{"0":6,"e":12},{"0":6,"e":13},{"0":6,"e":12},{"0":6,"e":13},{"0":6,"e":14},{"0":6,"e":12},{"0":5,"e":10},{"0":5,"e":12},{"0":4,"e":12},{"0":4,"e":8},{"0":3,"e":7},{"0":3,"e":7},{"0":3,"e":6},{"0":3,"e":6},{"0":3,"e":6},{"0":3,"e":7},{"0":2,"e":4},{"0":2,"e":5},{"0":2,"e":4},{"0":2,"e":4},{"0":2,"e":4},{"0":2,"e":4},{"0":2,"e":4},{"0":1,"e":2}]}],"D":[{"0":6,"d":177,"E":[{"0":6,"e":24},{"0":6,"e":24},{"0":6,"e":29},{"0":6,"e":37},{"0":6,"e":32},{"0":6,"e":23},{"0":6,"e":30},{"0":6,"e":29},{"0":6,"e":29},{"0":6,"e":25},{"0":6,"e":30},{"0":6,"e":30},{"0":6,"e":34},{"0":6,"e":46},{"0":6,"e":28},{"0":6,"e":34},{"0":6,"e":35},{"0":6,"e":28},{"0":6,"e":33},{"0":6,"e":37},{"0":6,"e":28},{"0":5,"e":22},{"0":5,"e":35},{"0":4,"e":24},{"0":4,"e":22},{"0":3,"e":15},{"0":3,"e":23},{"0":3,"e":14},{"0":3,"e":13},{"0":3,"e":12},{"0":3,"e":21},{"0":2,"e":11},{"0":2,"e":13},{"0":2,"e":18},{"0":2,"e":9},{"0":2,"e":15},{"0":2,"e":8},{"0":2,"e":9},{"0":1,"e":3}]}]},{"0":6,"c":7,"C":[{"0":6,"d":12,"E":[{"0":6,"e":16},{"0":2,"e":5},{"0":2,"e":5},{"0":2,"e":4}]},{"0":1,"d":4,"E":[{"0":1,"e":7},{"0":1,"e":2},{"0":1,"e":2},{"0":1,"e":1}]}],"D":[{"0":6,"d":12,"E":[{"0":6,"e":16},{"0":2,"e":10},{"0":2,"e":11},{"0":2,"e":13}]},{"0":1,"d":4,"E":[{"0":1,"e":7},{"0":1,"e":6},{"0":1,"e":4},{"0":1,"e":3}]}]}]},{"0":6,"b":12,"B":[{"0":6,"c":6,"C":[{"0":6,"d":158,"E":[{"0":6,"e":24},{"0":6,"e":12},{"0":6,"e":12},{"0":6,"e":12},{"0":6,"e":14},{"0":6,"e":12},{"0":6,"e":13},{"0":6,"e":13},{"0":6,"e":14},{"0":6,"e":12},{"0":6,"e":13},{"0":6,"e":12},{"0":6,"e":12},{"0":6,"e":12},{"0":6,"e":15},{"0":6,"e":12},{"0":6,"e":15},{"0":6,"e":13},{"0":6,"e":18},{"0":6,"e":13},{"0":5,"e":12},{"0":5,"e":10},{"0":5,"e":10},{"0":5,"e":10},{"0":4,"e":8},{"0":3,"e":6},{"0":3,"e":6},{"0":2,"e":5},{"0":1,"e":3},{"0":1,"e":2},{"0":1,"e":2},{"0":1,"e":2},{"0":1,"e":2},{"0":1,"e":2}]}],"D":[{"0":6,"d":158,"E":[{"0":6,"e":29},{"0":6,"e":20},{"0":6,"e":26},{"0":6,"e":32},{"0":6,"e":40},{"0":6,"e":29},{"0":6,"e":30},{"0":6,"e":24},{"0":6,"e":29},{"0":6,"e":40},{"0":6,"e":34},{"0":6,"e":30},{"0":6,"e":29},{"0":6,"e":30},{"0":6,"e":38},{"0":6,"e":37},{"0":6,"e":33},{"0":6,"e":31},{"0":6,"e":31},{"0":6,"e":33},{"0":5,"e":26},{"0":5,"e":27},{"0":5,"e":18},{"0":5,"e":28},{"0":4,"e":23},{"0":3,"e":11},{"0":3,"e":23},{"0":2,"e":13},{"0":1,"e":4},{"0":1,"e":7},{"0":1,"e":4},{"0":1,"e":4},{"0":1,"e":3},{"0":1,"e":8}]}]},{"0":6,"c":6,"C":[{"0":6,"d":9,"E":[{"0":6,"e":12},{"0":1,"e":2},{"0":1,"e":6},{"0":1,"e":1}]}],"D":[{"0":6,"d":9,"E":[{"0":6,"e":12},{"0":1,"e":5},{"0":1,"e":8},{"0":1,"e":3}]}]}]},{"0":6,"b":12,"B":[{"0":6,"c":6,"C":[{"0":6,"d":112,"E":[{"0":6,"e":24},{"0":6,"e":12},{"0":6,"e":13},{"0":6,"e":15},{"0":6,"e":14},{"0":6,"e":12},{"0":6,"e":13},{"0":6,"e":13},{"0":4,"e":8},{"0":3,"e":7},{"0":3,"e":8},{"0":3,"e":7},{"0":3,"e":7},{"0":3,"e":6},{"0":3,"e":6},{"0":3,"e":6},{"0":3,"e":6},{"0":3,"e":6},{"0":2,"e":5},{"0":2,"e":4},{"0":2,"e":4},{"0":2,"e":5},{"0":2,"e":4},{"0":2,"e":4},{"0":2,"e":5},{"0":2,"e":4},{"0":2,"e":4},{"0":2,"e":4},{"0":2,"e":4},{"0":1,"e":2},{"0":1,"e":2},{"0":1,"e":3},{"0":1,"e":2},{"0":1,"e":2},{"0":1,"e":2},{"0":1,"e":2},{"0":1,"e":2},{"0":1,"e":2},{"0":1,"e":2},{"0":1,"e":2}]}],"D":[{"0":6,"d":112,"E":[{"0":6,"e":29},{"0":6,"e":21},{"0":6,"e":29},{"0":6,"e":38},{"0":6,"e":34},{"0":6,"e":33},{"0":6,"e":29},{"0":6,"e":41},{"0":4,"e":27},{"0":3,"e":13},{"0":3,"e":17},{"0":3,"e":19},{"0":3,"e":14},{"0":3,"e":12},{"0":3,"e":21},{"0":3,"e":11},{"0":3,"e":12},{"0":3,"e":16},{"0":2,"e":19},{"0":2,"e":7},{"0":2,"e":14},{"0":2,"e":10},{"0":2,"e":14},{"0":2,"e":10},{"0":2,"e":9},{"0":2,"e":7},{"0":2,"e":9},{"0":2,"e":10},{"0":2,"e":15},{"0":1,"e":3},{"0":1,"e":4},{"0":1,"e":6},{"0":1,"e":4},{"0":1,"e":6},{"0":1,"e":7},{"0":1,"e":4},{"0":1,"e":5},{"0":1,"e":5},{"0":1,"e":5},{"0":1,"e":4}]}]},{"0":6,"c":6,"C":[{"0":6,"d":6,"E":[{"0":6,"e":6}]}],"D":[{"0":6,"d":6,"E":[{"0":6,"e":6}]}]}]},{"0":6,"b":12,"B":[{"0":6,"c":6,"C":[{"0":6,"d":174,"E":[{"0":6,"e":24},{"0":6,"e":12},{"0":6,"e":14},{"0":6,"e":13},{"0":6,"e":12},{"0":6,"e":12},{"0":6,"e":13},{"0":6,"e":15},{"0":5,"e":11},{"0":5,"e":11},{"0":5,"e":11},{"0":5,"e":10},{"0":5,"e":12},{"0":5,"e":10},{"0":5,"e":10},{"0":5,"e":11},{"0":5,"e":11},{"0":5,"e":10},{"0":5,"e":12},{"0":5,"e":10},{"0":5,"e":10},{"0":5,"e":11},{"0":5,"e":11},{"0":4,"e":9},{"0":4,"e":8},{"0":4,"e":9},{"0":4,"e":8},{"0":4,"e":8},{"0":3,"e":7},{"0":3,"e":6},{"0":3,"e":6},{"0":3,"e":6},{"0":3,"e":7},{"0":3,"e":9},{"0":3,"e":7},{"0":2,"e":4},{"0":2,"e":6},{"0":2,"e":4},{"0":2,"e":4},{"0":2,"e":4}]}],"D":[{"0":6,"d":174,"E":[{"0":6,"e":29},{"0":6,"e":25},{"0":6,"e":29},{"0":6,"e":38},{"0":6,"e":37},{"0":6,"e":24},{"0":6,"e":29},{"0":6,"e":44},{"0":5,"e":23},{"0":5,"e":29},{"0":5,"e":31},{"0":5,"e":19},{"0":5,"e":42},{"0":5,"e":20},{"0":5,"e":26},{"0":5,"e":36},{"0":5,"e":19},{"0":5,"e":21},{"0":5,"e":30},{"0":5,"e":22},{"0":5,"e":29},{"0":5,"e":34},{"0":5,"e":19},{"0":4,"e":25},{"0":4,"e":23},{"0":4,"e":24},{"0":4,"e":21},{"0":4,"e":24},{"0":3,"e":15},{"0":3,"e":24},{"0":3,"e":12},{"0":3,"e":24},{"0":3,"e":19},{"0":3,"e":13},{"0":3,"e":17},{"0":2,"e":12},{"0":2,"e":11},{"0":2,"e":14},{"0":2,"e":6},{"0":2,"e":12}]}]},{"0":6,"c":6,"C":[{"0":6,"d":8,"E":[{"0":6,"e":10},{"0":1,"e":2},{"0":1,"e":7}]}],"D":[{"0":6,"d":8,"E":[{"0":6,"e":10},{"0":1,"e":5},{"0":1,"e":10}]}]}]},{"0":6,"b":12,"B":[{"0":6,"c":6,"C":[{"0":6,"d":159,"E":[{"0":6,"e":24},{"0":6,"e":13},{"0":6,"e":19},{"0":6,"e":13},{"0":6,"e":14},{"0":6,"e":12},{"0":6,"e":14},{"0":6,"e":14},{"0":5,"e":12},{"0":5,"e":11},{"0":5,"e":12},{"0":5,"e":12},{"0":5,"e":10},{"0":5,"e":10},{"0":5,"e":10},{"0":5,"e":10},{"0":5,"e":10},{"0":4,"e":10},{"0":4,"e":8},{"0":3,"e":6},{"0":3,"e":6},{"0":3,"e":7},{"0":3,"e":6},{"0":3,"e":6},{"0":3,"e":6},{"0":3,"e":7},{"0":3,"e":6},{"0":3,"e":7},{"0":3,"e":7},{"0":3,"e":6},{"0":3,"e":6},{"0":2,"e":5},{"0":2,"e":5},{"0":2,"e":4},{"0":2,"e":4},{"0":2,"e":5},{"0":2,"e":4},{"0":2,"e":5},{"0":2,"e":4},{"0":2,"e":12},{"0":1,"e":2},{"0":1,"e":4},{"0":1,"e":2},{"0":1,"e":4}]}],"D":[{"0":6,"d":159,"E":[{"0":6,"e":29},{"0":6,"e":26},{"0":6,"e":33},{"0":6,"e":35},{"0":6,"e":26},{"0":6,"e":34},{"0":6,"e":26},{"0":6,"e":35},{"0":5,"e":28},{"0":5,"e":23},{"0":5,"e":25},{"0":5,"e":23},{"0":5,"e":28},{"0":5,"e":15},{"0":5,"e":27},{"0":5,"e":33},{"0":5,"e":24},{"0":4,"e":36},{"0":4,"e":18},{"0":3,"e":13},{"0":3,"e":13},{"0":3,"e":18},{"0":3,"e":15},{"0":3,"e":10},{"0":3,"e":17},{"0":3,"e":17},{"0":3,"e":11},{"0":3,"e":22},{"0":3,"e":11},{"0":3,"e":17},{"0":3,"e":24},{"0":2,"e":16},{"0":2,"e":10},{"0":2,"e":12},{"0":2,"e":8},{"0":2,"e":10},{"0":2,"e":11},{"0":2,"e":12},{"0":2,"e":9},{"0":2,"e":18},{"0":1,"e":2},{"0":1,"e":5},{"0":1,"e":4},{"0":1,"e":7}]}]},{"0":6,"c":9,"C":[{"0":6,"d":9,"E":[{"0":6,"e":12},{"0":1,"e":2},{"0":1,"e":6},{"0":1,"e":1}]},{"0":1,"d":3,"E":[{"0":1,"e":3},{"0":1,"e":2},{"0":1,"e":1}]},{"0":1,"d":3,"E":[{"0":1,"e":3},{"0":1,"e":2},{"0":1,"e":1}]},{"0":1,"d":3,"E":[{"0":1,"e":3},{"0":1,"e":2},{"0":1,"e":1}]}],"D":[{"0":6,"d":9,"E":[{"0":6,"e":12},{"0":1,"e":6},{"0":1,"e":9},{"0":1,"e":2}]},{"0":1,"d":3,"E":[{"0":1,"e":6},{"0":1,"e":4},{"0":1,"e":3}]},{"0":1,"d":3,"E":[{"0":1,"e":7},{"0":1,"e":3},{"0":1,"e":3}]},{"0":1,"d":3,"E":[{"0":1,"e":6},{"0":1,"e":3},{"0":1,"e":3}]}]}]},{"0":6,"b":12,"B":[{"0":6,"c":6,"C":[{"0":6,"d":180,"E":[{"0":6,"e":24},{"0":6,"e":12},{"0":6,"e":13},{"0":6,"e":12},{"0":6,"e":14},{"0":6,"e":13},{"0":6,"e":12},{"0":6,"e":12},{"0":5,"e":11},{"0":5,"e":13},{"0":5,"e":11},{"0":5,"e":10},{"0":5,"e":11},{"0":5,"e":10},{"0":4,"e":9},{"0":4,"e":11},{"0":4,"e":10},{"0":4,"e":8},{"0":4,"e":9},{"0":4,"e":9},{"0":4,"e":9},{"0":3,"e":6},{"0":3,"e":7},{"0":3,"e":7},{"0":3,"e":6},{"0":3,"e":6},{"0":3,"e":10},{"0":3,"e":6},{"0":3,"e":7},{"0":3,"e":6},{"0":3,"e":6},{"0":3,"e":6},{"0":3,"e":7},{"0":3,"e":6},{"0":3,"e":6},{"0":3,"e":7},{"0":3,"e":7},{"0":3,"e":6},{"0":3,"e":6},{"0":3,"e":6},{"0":3,"e":6},{"0":2,"e":4},{"0":2,"e":4},{"0":2,"e":5},{"0":2,"e":4},{"0":1,"e":2},{"0":1,"e":2},{"0":1,"e":2},{"0":1,"e":2},{"0":1,"e":2},{"0":1,"e":2}]}],"D":[{"0":6,"d":180,"E":[{"0":6,"e":29},{"0":6,"e":22},{"0":6,"e":29},{"0":6,"e":35},{"0":6,"e":27},{"0":6,"e":33},{"0":6,"e":29},{"0":6,"e":30},{"0":5,"e":24},{"0":5,"e":27},{"0":5,"e":31},{"0":5,"e":24},{"0":5,"e":28},{"0":5,"e":26},{"0":4,"e":21},{"0":4,"e":20},{"0":4,"e":25},{"0":4,"e":20},{"0":4,"e":24},{"0":4,"e":20},{"0":4,"e":23},{"0":3,"e":13},{"0":3,"e":18},{"0":3,"e":20},{"0":3,"e":11},{"0":3,"e":17},{"0":3,"e":21},{"0":3,"e":12},{"0":3,"e":13},{"0":3,"e":18},{"0":3,"e":11},{"0":3,"e":15},{"0":3,"e":23},{"0":3,"e":11},{"0":3,"e":11},{"0":3,"e":16},{"0":3,"e":21},{"0":3,"e":13},{"0":3,"e":10},{"0":3,"e":10},{"0":3,"e":25},{"0":2,"e":11},{"0":2,"e":13},{"0":2,"e":13},{"0":2,"e":14},{"0":1,"e":4},{"0":1,"e":3},{"0":1,"e":4},{"0":1,"e":7},{"0":1,"e":3},{"0":1,"e":3}]}]},{"0":6,"c":6,"C":[{"0":6,"d":8,"E":[{"0":6,"e":10},{"0":1,"e":3},{"0":1,"e":4}]}],"D":[{"0":6,"d":8,"E":[{"0":6,"e":10},{"0":1,"e":4},{"0":1,"e":8}]}]}]},{"0":6,"b":12,"B":[{"0":6,"c":6,"C":[{"0":6,"d":220,"E":[{"0":6,"e":24},{"0":6,"e":12},{"0":6,"e":12},{"0":6,"e":13},{"0":6,"e":12},{"0":6,"e":13},{"0":6,"e":13},{"0":6,"e":13},{"0":6,"e":12},{"0":6,"e":12},{"0":6,"e":14},{"0":6,"e":15},{"0":6,"e":13},{"0":6,"e":13},{"0":6,"e":15},{"0":6,"e":12},{"0":6,"e":12},{"0":6,"e":12},{"0":6,"e":13},{"0":6,"e":12},{"0":5,"e":10},{"0":4,"e":12},{"0":4,"e":8},{"0":4,"e":8},{"0":4,"e":8},{"0":4,"e":9},{"0":4,"e":8},{"0":3,"e":7},{"0":3,"e":7},{"0":3,"e":6},{"0":2,"e":5},{"0":2,"e":4},{"0":2,"e":4},{"0":2,"e":4},{"0":2,"e":5},{"0":2,"e":4},{"0":2,"e":4},{"0":2,"e":4},{"0":2,"e":5},{"0":2,"e":8},{"0":2,"e":6},{"0":2,"e":8},{"0":2,"e":4},{"0":2,"e":4},{"0":2,"e":4},{"0":2,"e":5},{"0":2,"e":6},{"0":2,"e":4},{"0":2,"e":5},{"0":2,"e":5},{"0":2,"e":4},{"0":2,"e":5},{"0":2,"e":4},{"0":2,"e":5},{"0":1,"e":3},{"0":1,"e":2},{"0":1,"e":2},{"0":1,"e":2},{"0":1,"e":2},{"0":1,"e":2},{"0":1,"e":2},{"0":1,"e":2},{"0":1,"e":2},{"0":1,"e":2},{"0":1,"e":2},{"0":1,"e":2},{"0":1,"e":2},{"0":1,"e":2}]}],"D":[{"0":6,"d":220,"E":[{"0":6,"e":30},{"0":6,"e":27},{"0":6,"e":25},{"0":6,"e":41},{"0":6,"e":21},{"0":6,"e":40},{"0":6,"e":30},{"0":6,"e":34},{"0":6,"e":37},{"0":6,"e":22},{"0":6,"e":34},{"0":6,"e":34},{"0":6,"e":35},{"0":6,"e":28},{"0":6,"e":46},{"0":6,"e":39},{"0":6,"e":29},{"0":6,"e":32},{"0":6,"e":32},{"0":6,"e":35},{"0":5,"e":25},{"0":4,"e":27},{"0":4,"e":17},{"0":4,"e":19},{"0":4,"e":21},{"0":4,"e":23},{"0":4,"e":19},{"0":3,"e":16},{"0":3,"e":18},{"0":3,"e":22},{"0":2,"e":11},{"0":2,"e":7},{"0":2,"e":9},{"0":2,"e":8},{"0":2,"e":11},{"0":2,"e":10},{"0":2,"e":9},{"0":2,"e":16},{"0":2,"e":14},{"0":2,"e":11},{"0":2,"e":7},{"0":2,"e":11},{"0":2,"e":8},{"0":2,"e":15},{"0":2,"e":7},{"0":2,"e":16},{"0":2,"e":9},{"0":2,"e":14},{"0":2,"e":10},{"0":2,"e":15},{"0":2,"e":14},{"0":2,"e":14},{"0":2,"e":9},{"0":2,"e":20},{"0":1,"e":5},{"0":1,"e":4},{"0":1,"e":7},{"0":1,"e":3},{"0":1,"e":4},{"0":1,"e":5},{"0":1,"e":3},{"0":1,"e":7},{"0":1,"e":3},{"0":1,"e":4},{"0":1,"e":11},{"0":1,"e":3},{"0":1,"e":4},{"0":1,"e":13}]}]},{"0":6,"c":6,"C":[{"0":6,"d":6,"E":[{"0":6,"e":6}]}],"D":[{"0":6,"d":6,"E":[{"0":6,"e":6}]}]}]},{"0":6,"b":12,"B":[{"0":6,"c":6,"C":[{"0":6,"d":150,"E":[{"0":6,"e":24},{"0":6,"e":12},{"0":6,"e":13},{"0":6,"e":12},{"0":6,"e":12},{"0":6,"e":12},{"0":6,"e":14},{"0":6,"e":13},{"0":5,"e":13},{"0":5,"e":13},{"0":5,"e":12},{"0":5,"e":13},{"0":5,"e":10},{"0":5,"e":12},{"0":4,"e":10},{"0":4,"e":9},{"0":3,"e":6},{"0":3,"e":6},{"0":3,"e":6},{"0":3,"e":7},{"0":2,"e":4},{"0":2,"e":4},{"0":2,"e":8},{"0":2,"e":5},{"0":2,"e":5},{"0":2,"e":4},{"0":2,"e":5},{"0":2,"e":4},{"0":2,"e":4},{"0":2,"e":5},{"0":2,"e":4},{"0":2,"e":4},{"0":2,"e":8},{"0":2,"e":4},{"0":2,"e":5},{"0":2,"e":6},{"0":1,"e":2},{"0":1,"e":2},{"0":1,"e":2},{"0":1,"e":2},{"0":1,"e":2},{"0":1,"e":3},{"0":1,"e":2},{"0":1,"e":2},{"0":1,"e":2},{"0":1,"e":2},{"0":1,"e":2},{"0":1,"e":5},{"0":1,"e":2},{"0":1,"e":2},{"0":1,"e":3},{"0":1,"e":2},{"0":1,"e":2},{"0":1,"e":2},{"0":1,"e":2},{"0":1,"e":2}]}],"D":[{"0":6,"d":150,"E":[{"0":6,"e":30},{"0":6,"e":21},{"0":6,"e":33},{"0":6,"e":38},{"0":6,"e":34},{"0":6,"e":36},{"0":6,"e":24},{"0":6,"e":38},{"0":5,"e":23},{"0":5,"e":26},{"0":5,"e":22},{"0":5,"e":30},{"0":5,"e":25},{"0":5,"e":30},{"0":4,"e":25},{"0":4,"e":30},{"0":3,"e":12},{"0":3,"e":12},{"0":3,"e":19},{"0":3,"e":20},{"0":2,"e":9},{"0":2,"e":12},{"0":2,"e":10},{"0":2,"e":13},{"0":2,"e":20},{"0":2,"e":10},{"0":2,"e":12},{"0":2,"e":10},{"0":2,"e":10},{"0":2,"e":16},{"0":2,"e":8},{"0":2,"e":10},{"0":2,"e":9},{"0":2,"e":14},{"0":2,"e":12},{"0":2,"e":11},{"0":1,"e":4},{"0":1,"e":10},{"0":1,"e":3},{"0":1,"e":4},{"0":1,"e":4},{"0":1,"e":12},{"0":1,"e":4},{"0":1,"e":3},{"0":1,"e":4},{"0":1,"e":5},{"0":1,"e":8},{"0":1,"e":6},{"0":1,"e":3},{"0":1,"e":4},{"0":1,"e":11},{"0":1,"e":4},{"0":1,"e":3},{"0":1,"e":4},{"0":1,"e":8},{"0":1,"e":8}]}]},{"0":6,"c":7,"C":[{"0":6,"d":11,"E":[{"0":6,"e":16},{"0":2,"e":4},{"0":2,"e":6},{"0":1,"e":1}]},{"0":1,"d":4,"E":[{"0":1,"e":7},{"0":1,"e":2},{"0":1,"e":6},{"0":1,"e":1}]}],"D":[{"0":6,"d":11,"E":[{"0":6,"e":16},{"0":2,"e":11},{"0":2,"e":12},{"0":1,"e":3}]},{"0":1,"d":4,"E":[{"0":1,"e":7},{"0":1,"e":6},{"0":1,"e":9},{"0":1,"e":3}]}]}]},{"0":6,"b":12,"B":[{"0":6,"c":6,"C":[{"0":6,"d":144,"E":[{"0":6,"e":24},{"0":6,"e":16},{"0":6,"e":13},{"0":6,"e":12},{"0":6,"e":14},{"0":6,"e":12},{"0":6,"e":12},{"0":6,"e":14},{"0":5,"e":10},{"0":5,"e":10},{"0":5,"e":11},{"0":5,"e":12},{"0":4,"e":9},{"0":4,"e":8},{"0":4,"e":9},{"0":4,"e":11},{"0":4,"e":8},{"0":3,"e":6},{"0":3,"e":6},{"0":3,"e":6},{"0":3,"e":6},{"0":3,"e":7},{"0":3,"e":7},{"0":3,"e":6},{"0":3,"e":6},{"0":3,"e":7},{"0":3,"e":6},{"0":3,"e":7},{"0":3,"e":6},{"0":3,"e":7},{"0":3,"e":9},{"0":3,"e":6},{"0":3,"e":6},{"0":3,"e":6},{"0":1,"e":2},{"0":1,"e":2},{"0":1,"e":2},{"0":1,"e":2},{"0":1,"e":2}]}],"D":[{"0":6,"d":144,"E":[{"0":6,"e":30},{"0":6,"e":21},{"0":6,"e":25},{"0":6,"e":35},{"0":6,"e":39},{"0":6,"e":26},{"0":6,"e":26},{"0":6,"e":46},{"0":5,"e":20},{"0":5,"e":25},{"0":5,"e":32},{"0":5,"e":33},{"0":4,"e":27},{"0":4,"e":17},{"0":4,"e":19},{"0":4,"e":21},{"0":4,"e":25},{"0":3,"e":10},{"0":3,"e":14},{"0":3,"e":13},{"0":3,"e":20},{"0":3,"e":14},{"0":3,"e":14},{"0":3,"e":21},{"0":3,"e":15},{"0":3,"e":21},{"0":3,"e":14},{"0":3,"e":16},{"0":3,"e":14},{"0":3,"e":18},{"0":3,"e":18},{"0":3,"e":15},{"0":3,"e":14},{"0":3,"e":18},{"0":1,"e":4},{"0":1,"e":6},{"0":1,"e":3},{"0":1,"e":6},{"0":1,"e":10}]}]},{"0":6,"c":9,"C":[{"0":6,"d":9,"E":[{"0":6,"e":12},{"0":1,"e":2},{"0":1,"e":2},{"0":1,"e":1}]},{"0":1,"d":3,"E":[{"0":1,"e":3},{"0":1,"e":2},{"0":1,"e":1}]},{"0":1,"d":3,"E":[{"0":1,"e":3},{"0":1,"e":2},{"0":1,"e":1}]},{"0":1,"d":4,"E":[{"0":1,"e":3},{"0":1,"e":2},{"0":1,"e":6},{"0":1,"e":1}]}],"D":[{"0":6,"d":9,"E":[{"0":6,"e":12},{"0":1,"e":5},{"0":1,"e":4},{"0":1,"e":3}]},{"0":1,"d":3,"E":[{"0":1,"e":7},{"0":1,"e":3},{"0":1,"e":3}]},{"0":1,"d":3,"E":[{"0":1,"e":7},{"0":1,"e":4},{"0":1,"e":3}]},{"0":1,"d":4,"E":[{"0":1,"e":3},{"0":1,"e":7},{"0":1,"e":7},{"0":1,"e":2}]}]}]},{"0":6,"b":12,"B":[{"0":6,"c":6,"C":[{"0":6,"d":168,"E":[{"0":6,"e":24},{"0":6,"e":16},{"0":6,"e":13},{"0":6,"e":14},{"0":6,"e":12},{"0":6,"e":12},{"0":6,"e":13},{"0":6,"e":13},{"0":5,"e":10},{"0":5,"e":10},{"0":5,"e":13},{"0":5,"e":10},{"0":5,"e":12},{"0":5,"e":11},{"0":5,"e":11},{"0":5,"e":11},{"0":5,"e":10},{"0":3,"e":6},{"0":3,"e":7},{"0":3,"e":6},{"0":3,"e":7},{"0":3,"e":6},{"0":3,"e":6},{"0":3,"e":6},{"0":3,"e":7},{"0":3,"e":6},{"0":3,"e":8},{"0":3,"e":7},{"0":3,"e":7},{"0":3,"e":7},{"0":3,"e":6},{"0":3,"e":7},{"0":3,"e":6},{"0":3,"e":6},{"0":2,"e":6},{"0":2,"e":4},{"0":2,"e":4},{"0":2,"e":4},{"0":2,"e":4},{"0":2,"e":6},{"0":2,"e":4},{"0":2,"e":4},{"0":2,"e":4},{"0":2,"e":4},{"0":2,"e":4},{"0":1,"e":2},{"0":1,"e":2}]}],"D":[{"0":6,"d":168,"E":[{"0":6,"e":30},{"0":6,"e":23},{"0":6,"e":27},{"0":6,"e":32},{"0":6,"e":32},{"0":6,"e":29},{"0":6,"e":29},{"0":6,"e":27},{"0":5,"e":25},{"0":5,"e":28},{"0":5,"e":26},{"0":5,"e":26},{"0":5,"e":35},{"0":5,"e":26},{"0":5,"e":34},{"0":5,"e":27},{"0":5,"e":26},{"0":3,"e":21},{"0":3,"e":15},{"0":3,"e":17},{"0":3,"e":21},{"0":3,"e":21},{"0":3,"e":12},{"0":3,"e":13},{"0":3,"e":16},{"0":3,"e":14},{"0":3,"e":16},{"0":3,"e":15},{"0":3,"e":18},{"0":3,"e":22},{"0":3,"e":12},{"0":3,"e":20},{"0":3,"e":14},{"0":3,"e":18},{"0":2,"e":10},{"0":2,"e":6},{"0":2,"e":8},{"0":2,"e":10},{"0":2,"e":10},{"0":2,"e":12},{"0":2,"e":12},{"0":2,"e":9},{"0":2,"e":18},{"0":2,"e":7},{"0":2,"e":10},{"0":1,"e":6},{"0":1,"e":10}]}]},{"0":6,"c":6,"C":[{"0":6,"d":9,"E":[{"0":6,"e":12},{"0":1,"e":2},{"0":1,"e":2},{"0":1,"e":1}]}],"D":[{"0":6,"d":9,"E":[{"0":6,"e":12},{"0":1,"e":5},{"0":1,"e":4},{"0":1,"e":3}]}]}]},{"0":6,"b":12,"B":[{"0":6,"c":6,"C":[{"0":6,"d":170,"E":[{"0":6,"e":24},{"0":6,"e":12},{"0":6,"e":13},{"0":6,"e":13},{"0":6,"e":12},{"0":6,"e":13},{"0":6,"e":12},{"0":6,"e":12},{"0":5,"e":11},{"0":5,"e":13},{"0":5,"e":11},{"0":5,"e":14},{"0":5,"e":12},{"0":5,"e":10},{"0":5,"e":11},{"0":4,"e":8},{"0":4,"e":8},{"0":3,"e":6},{"0":3,"e":6},{"0":3,"e":7},{"0":3,"e":7},{"0":3,"e":7},{"0":3,"e":6},{"0":3,"e":7},{"0":3,"e":6},{"0":3,"e":6},{"0":3,"e":6},{"0":3,"e":9},{"0":3,"e":6},{"0":3,"e":6},{"0":3,"e":6},{"0":3,"e":10},{"0":3,"e":7},{"0":3,"e":7},{"0":3,"e":6},{"0":3,"e":7},{"0":3,"e":7},{"0":3,"e":7},{"0":3,"e":6},{"0":3,"e":6},{"0":2,"e":4},{"0":2,"e":4},{"0":1,"e":2},{"0":1,"e":2},{"0":1,"e":2},{"0":1,"e":2},{"0":1,"e":2},{"0":1,"e":2}]}],"D":[{"0":6,"d":170,"E":[{"0":6,"e":30},{"0":6,"e":23},{"0":6,"e":26},{"0":6,"e":37},{"0":6,"e":28},{"0":6,"e":35},{"0":6,"e":24},{"0":6,"e":32},{"0":5,"e":35},{"0":5,"e":25},{"0":5,"e":22},{"0":5,"e":28},{"0":5,"e":28},{"0":5,"e":26},{"0":5,"e":34},{"0":4,"e":22},{"0":4,"e":20},{"0":3,"e":11},{"0":3,"e":14},{"0":3,"e":18},{"0":3,"e":17},{"0":3,"e":16},{"0":3,"e":19},{"0":3,"e":14},{"0":3,"e":14},{"0":3,"e":17},{"0":3,"e":11},{"0":3,"e":16},{"0":3,"e":15},{"0":3,"e":15},{"0":3,"e":23},{"0":3,"e":19},{"0":3,"e":17},{"0":3,"e":21},{"0":3,"e":13},{"0":3,"e":17},{"0":3,"e":18},{"0":3,"e":10},{"0":3,"e":13},{"0":3,"e":23},{"0":2,"e":8},{"0":2,"e":12},{"0":1,"e":7},{"0":1,"e":6},{"0":1,"e":5},{"0":1,"e":8},{"0":1,"e":4},{"0":1,"e":6}]}]},{"0":6,"c":7,"C":[{"0":6,"d":14,"E":[{"0":6,"e":10},{"0":1,"e":3},{"0":1,"e":2},{"0":1,"e":3},{"0":1,"e":2},{"0":1,"e":2},{"0":1,"e":2},{"0":1,"e":2},{"0":1,"e":3}]},{"0":1,"d":5,"E":[{"0":1,"e":5},{"0":1,"e":2},{"0":1,"e":3},{"0":1,"e":2},{"0":1,"e":3}]}],"D":[{"0":6,"d":14,"E":[{"0":6,"e":10},{"0":1,"e":4},{"0":1,"e":6},{"0":1,"e":4},{"0":1,"e":4},{"0":1,"e":6},{"0":1,"e":3},{"0":1,"e":4},{"0":1,"e":9}]},{"0":1,"d":5,"E":[{"0":1,"e":5},{"0":1,"e":5},{"0":1,"e":7},{"0":1,"e":4},{"0":1,"e":9}]}]}]},{"0":6,"b":12,"B":[{"0":6,"c":6,"C":[{"0":6,"d":141,"E":[{"0":6,"e":24},{"0":6,"e":12},{"0":6,"e":13},{"0":6,"e":12},{"0":6,"e":13},{"0":6,"e":13},{"0":6,"e":12},{"0":6,"e":15},{"0":5,"e":12},{"0":5,"e":12},{"0":5,"e":10},{"0":5,"e":11},{"0":5,"e":11},{"0":5,"e":15},{"0":5,"e":15},{"0":5,"e":10},{"0":5,"e":12},{"0":5,"e":11},{"0":4,"e":9},{"0":4,"e":9},{"0":4,"e":9},{"0":4,"e":8},{"0":4,"e":8},{"0":4,"e":8},{"0":4,"e":8},{"0":3,"e":6},{"0":2,"e":4},{"0":2,"e":5},{"0":1,"e":2},{"0":1,"e":2},{"0":1,"e":2},{"0":1,"e":2},{"0":1,"e":2},{"0":1,"e":2},{"0":1,"e":2},{"0":1,"e":2}]}],"D":[{"0":6,"d":141,"E":[{"0":6,"e":30},{"0":6,"e":23},{"0":6,"e":29},{"0":6,"e":33},{"0":6,"e":29},{"0":6,"e":28},{"0":6,"e":24},{"0":6,"e":30},{"0":5,"e":28},{"0":5,"e":35},{"0":5,"e":24},{"0":5,"e":27},{"0":5,"e":34},{"0":5,"e":25},{"0":5,"e":26},{"0":5,"e":33},{"0":5,"e":19},{"0":5,"e":31},{"0":4,"e":23},{"0":4,"e":23},{"0":4,"e":24},{"0":4,"e":18},{"0":4,"e":19},{"0":4,"e":16},{"0":4,"e":27},{"0":3,"e":19},{"0":2,"e":12},{"0":2,"e":18},{"0":1,"e":4},{"0":1,"e":6},{"0":1,"e":5},{"0":1,"e":4},{"0":1,"e":9},{"0":1,"e":4},{"0":1,"e":6},{"0":1,"e":5}]}]},{"0":6,"c":6,"C":[{"0":6,"d":9,"E":[{"0":6,"e":12},{"0":1,"e":2},{"0":1,"e":2},{"0":1,"e":1}]}],"D":[{"0":6,"d":9,"E":[{"0":6,"e":12},{"0":1,"e":6},{"0":1,"e":4},{"0":1,"e":3}]}]}]},{"0":6,"b":12,"B":[{"0":6,"c":6,"C":[{"0":6,"d":162,"E":[{"0":6,"e":24},{"0":6,"e":12},{"0":6,"e":16},{"0":6,"e":15},{"0":6,"e":14},{"0":6,"e":12},{"0":6,"e":12},{"0":6,"e":14},{"0":6,"e":13},{"0":5,"e":10},{"0":5,"e":12},{"0":5,"e":13},{"0":5,"e":12},{"0":5,"e":10},{"0":5,"e":12},{"0":5,"e":10},{"0":5,"e":12},{"0":5,"e":12},{"0":5,"e":10},{"0":4,"e":8},{"0":3,"e":8},{"0":3,"e":6},{"0":2,"e":8},{"0":2,"e":4},{"0":2,"e":4},{"0":2,"e":4},{"0":2,"e":4},{"0":2,"e":5},{"0":2,"e":4},{"0":2,"e":4},{"0":2,"e":4},{"0":2,"e":4},{"0":2,"e":5},{"0":2,"e":4},{"0":2,"e":5},{"0":2,"e":6},{"0":2,"e":4},{"0":2,"e":4},{"0":2,"e":4},{"0":2,"e":4},{"0":2,"e":4},{"0":2,"e":8},{"0":2,"e":4},{"0":2,"e":4},{"0":2,"e":4},{"0":1,"e":2},{"0":1,"e":2}]}],"D":[{"0":6,"d":162,"E":[{"0":6,"e":30},{"0":6,"e":25},{"0":6,"e":32},{"0":6,"e":31},{"0":6,"e":34},{"0":6,"e":32},{"0":6,"e":25},{"0":6,"e":45},{"0":6,"e":43},{"0":5,"e":18},{"0":5,"e":26},{"0":5,"e":29},{"0":5,"e":26},{"0":5,"e":22},{"0":5,"e":36},{"0":5,"e":33},{"0":5,"e":23},{"0":5,"e":29},{"0":5,"e":29},{"0":4,"e":18},{"0":3,"e":23},{"0":3,"e":23},{"0":2,"e":14},{"0":2,"e":10},{"0":2,"e":9},{"0":2,"e":7},{"0":2,"e":12},{"0":2,"e":9},{"0":2,"e":13},{"0":2,"e":8},{"0":2,"e":10},{"0":2,"e":8},{"0":2,"e":14},{"0":2,"e":8},{"0":2,"e":11},{"0":2,"e":10},{"0":2,"e":8},{"0":2,"e":10},{"0":2,"e":7},{"0":2,"e":12},{"0":2,"e":7},{"0":2,"e":12},{"0":2,"e":7},{"0":2,"e":8},{"0":2,"e":17},{"0":1,"e":3},{"0":1,"e":6}]}]},{"0":6,"c":6,"C":[{"0":6,"d":8,"E":[{"0":6,"e":10},{"0":1,"e":2},{"0":1,"e":4}]}],"D":[{"0":6,"d":8,"E":[{"0":6,"e":10},{"0":1,"e":5},{"0":1,"e":7}]}]}]},{"0":6,"b":12,"B":[{"0":6,"c":6,"C":[{"0":6,"d":129,"E":[{"0":6,"e":24},{"0":6,"e":12},{"0":6,"e":12},{"0":6,"e":12},{"0":6,"e":14},{"0":6,"e":13},{"0":6,"e":13},{"0":6,"e":13},{"0":6,"e":12},{"0":5,"e":11},{"0":5,"e":10},{"0":5,"e":10},{"0":5,"e":11},{"0":5,"e":12},{"0":5,"e":12},{"0":4,"e":12},{"0":4,"e":8},{"0":4,"e":8},{"0":4,"e":9},{"0":3,"e":6},{"0":3,"e":9},{"0":2,"e":6},{"0":2,"e":4},{"0":2,"e":5},{"0":2,"e":4},{"0":2,"e":4},{"0":2,"e":4},{"0":2,"e":4},{"0":2,"e":7},{"0":2,"e":5},{"0":2,"e":4},{"0":1,"e":2},{"0":1,"e":2},{"0":1,"e":2}]}],"D":[{"0":6,"d":129,"E":[{"0":6,"e":30},{"0":6,"e":24},{"0":6,"e":27},{"0":6,"e":31},{"0":6,"e":32},{"0":6,"e":36},{"0":6,"e":28},{"0":6,"e":38},{"0":6,"e":31},{"0":5,"e":25},{"0":5,"e":31},{"0":5,"e":26},{"0":5,"e":25},{"0":5,"e":27},{"0":5,"e":31},{"0":4,"e":24},{"0":4,"e":18},{"0":4,"e":19},{"0":4,"e":24},{"0":3,"e":11},{"0":3,"e":22},{"0":2,"e":13},{"0":2,"e":9},{"0":2,"e":10},{"0":2,"e":9},{"0":2,"e":13},{"0":2,"e":9},{"0":2,"e":11},{"0":2,"e":12},{"0":2,"e":12},{"0":2,"e":14},{"0":1,"e":4},{"0":1,"e":5},{"0":1,"e":8}]}]},{"0":6,"c":6,"C":[{"0":6,"d":6,"E":[{"0":6,"e":6}]}],"D":[{"0":6,"d":6,"E":[{"0":6,"e":6}]}]}]},{"0":6,"b":12,"B":[{"0":6,"c":6,"C":[{"0":6,"d":153,"E":[{"0":6,"e":24},{"0":6,"e":12},{"0":6,"e":12},{"0":6,"e":13},{"0":6,"e":12},{"0":6,"e":12},{"0":6,"e":12},{"0":6,"e":13},{"0":6,"e":13},{"0":6,"e":12},{"0":6,"e":14},{"0":6,"e":16},{"0":5,"e":10},{"0":5,"e":10},{"0":5,"e":11},{"0":5,"e":13},{"0":5,"e":10},{"0":5,"e":10},{"0":5,"e":11},{"0":4,"e":11},{"0":4,"e":8},{"0":3,"e":6},{"0":2,"e":5},{"0":2,"e":5},{"0":2,"e":4},{"0":2,"e":4},{"0":2,"e":4},{"0":2,"e":4},{"0":2,"e":4},{"0":2,"e":5},{"0":2,"e":4},{"0":2,"e":4},{"0":2,"e":4},{"0":1,"e":2},{"0":1,"e":2},{"0":1,"e":2},{"0":1,"e":3},{"0":1,"e":2},{"0":1,"e":2},{"0":1,"e":2},{"0":1,"e":2},{"0":1,"e":2},{"0":1,"e":3},{"0":1,"e":2},{"0":1,"e":2},{"0":1,"e":2}]}],"D":[{"0":6,"d":153,"E":[{"0":6,"e":30},{"0":6,"e":27},{"0":6,"e":34},{"0":6,"e":38},{"0":6,"e":26},{"0":6,"e":37},{"0":6,"e":41},{"0":6,"e":39},{"0":6,"e":36},{"0":6,"e":22},{"0":6,"e":38},{"0":6,"e":37},{"0":5,"e":21},{"0":5,"e":27},{"0":5,"e":29},{"0":5,"e":31},{"0":5,"e":26},{"0":5,"e":24},{"0":5,"e":32},{"0":4,"e":26},{"0":4,"e":29},{"0":3,"e":15},{"0":2,"e":15},{"0":2,"e":13},{"0":2,"e":6},{"0":2,"e":8},{"0":2,"e":11},{"0":2,"e":6},{"0":2,"e":10},{"0":2,"e":20},{"0":2,"e":13},{"0":2,"e":7},{"0":2,"e":17},{"0":1,"e":7},{"0":1,"e":3},{"0":1,"e":4},{"0":1,"e":7},{"0":1,"e":5},{"0":1,"e":7},{"0":1,"e":6},{"0":1,"e":4},{"0":1,"e":4},{"0":1,"e":8},{"0":1,"e":3},{"0":1,"e":6},{"0":1,"e":6}]}]},{"0":6,"c":6,"C":[{"0":6,"d":11,"E":[{"0":6,"e":10},{"0":1,"e":2},{"0":1,"e":3},{"0":1,"e":2},{"0":1,"e":2},{"0":1,"e":3}]}],"D":[{"0":6,"d":11,"E":[{"0":6,"e":10},{"0":1,"e":5},{"0":1,"e":4},{"0":1,"e":4},{"0":1,"e":4},{"0":1,"e":9}]}]}]},{"0":6,"b":12,"B":[{"0":6,"c":6,"C":[{"0":6,"d":121,"E":[{"0":6,"e":24},{"0":6,"e":12},{"0":6,"e":16},{"0":6,"e":14},{"0":6,"e":13},{"0":6,"e":13},{"0":6,"e":12},{"0":6,"e":12},{"0":5,"e":10},{"0":5,"e":10},{"0":5,"e":13},{"0":5,"e":10},{"0":5,"e":11},{"0":5,"e":11},{"0":5,"e":11},{"0":4,"e":12},{"0":3,"e":6},{"0":3,"e":6},{"0":3,"e":6},{"0":3,"e":7},{"0":2,"e":4},{"0":2,"e":4},{"0":2,"e":5},{"0":2,"e":4},{"0":2,"e":4},{"0":2,"e":4},{"0":2,"e":5},{"0":2,"e":5},{"0":2,"e":5},{"0":2,"e":4},{"0":1,"e":2},{"0":1,"e":2}]}],"D":[{"0":6,"d":121,"E":[{"0":6,"e":30},{"0":6,"e":24},{"0":6,"e":28},{"0":6,"e":34},{"0":6,"e":42},{"0":6,"e":25},{"0":6,"e":28},{"0":6,"e":28},{"0":5,"e":25},{"0":5,"e":28},{"0":5,"e":33},{"0":5,"e":20},{"0":5,"e":43},{"0":5,"e":31},{"0":5,"e":22},{"0":4,"e":33},{"0":3,"e":17},{"0":3,"e":12},{"0":3,"e":12},{"0":3,"e":19},{"0":2,"e":19},{"0":2,"e":10},{"0":2,"e":14},{"0":2,"e":10},{"0":2,"e":11},{"0":2,"e":11},{"0":2,"e":8},{"0":2,"e":13},{"0":2,"e":11},{"0":2,"e":11},{"0":1,"e":6},{"0":1,"e":5}]}]},{"0":6,"c":6,"C":[{"0":6,"d":8,"E":[{"0":6,"e":10},{"0":1,"e":3},{"0":1,"e":4}]}],"D":[{"0":6,"d":8,"E":[{"0":6,"e":10},{"0":1,"e":4},{"0":1,"e":11}]}]}]},{"0":6,"b":12,"B":[{"0":6,"c":6,"C":[{"0":6,"d":202,"E":[{"0":6,"e":24},{"0":6,"e":12},{"0":6,"e":14},{"0":6,"e":12},{"0":6,"e":12},{"0":6,"e":13},{"0":6,"e":12},{"0":6,"e":12},{"0":6,"e":14},{"0":6,"e":14},{"0":6,"e":13},{"0":6,"e":13},{"0":6,"e":12},{"0":6,"e":13},{"0":5,"e":11},{"0":5,"e":12},{"0":5,"e":11},{"0":5,"e":12},{"0":5,"e":11},{"0":5,"e":10},{"0":5,"e":11},{"0":5,"e":14},{"0":5,"e":10},{"0":5,"e":10},{"0":5,"e":11},{"0":5,"e":10},{"0":5,"e":13},{"0":5,"e":12},{"0":4,"e":8},{"0":4,"e":9},{"0":4,"e":9},{"0":4,"e":8},{"0":4,"e":8},{"0":3,"e":6},{"0":3,"e":6},{"0":3,"e":6},{"0":3,"e":6},{"0":2,"e":4},{"0":2,"e":5},{"0":2,"e":4},{"0":2,"e":4},{"0":2,"e":4},{"0":1,"e":2},{"0":1,"e":2},{"0":1,"e":2},{"0":1,"e":2},{"0":1,"e":2},{"0":1,"e":2}]}],"D":[{"0":6,"d":202,"E":[{"0":6,"e":30},{"0":6,"e":23},{"0":6,"e":28},{"0":6,"e":43},{"0":6,"e":24},{"0":6,"e":30},{"0":6,"e":38},{"0":6,"e":30},{"0":6,"e":36},{"0":6,"e":33},{"0":6,"e":24},{"0":6,"e":44},{"0":6,"e":37},{"0":6,"e":30},{"0":5,"e":36},{"0":5,"e":33},{"0":5,"e":23},{"0":5,"e":32},{"0":5,"e":32},{"0":5,"e":25},{"0":5,"e":34},{"0":5,"e":30},{"0":5,"e":19},{"0":5,"e":37},{"0":5,"e":28},{"0":5,"e":21},{"0":5,"e":24},{"0":5,"e":31},{"0":4,"e":20},{"0":4,"e":18},{"0":4,"e":20},{"0":4,"e":16},{"0":4,"e":29},{"0":3,"e":20},{"0":3,"e":14},{"0":3,"e":15},{"0":3,"e":20},{"0":2,"e":8},{"0":2,"e":19},{"0":2,"e":7},{"0":2,"e":9},{"0":2,"e":18},{"0":1,"e":5},{"0":1,"e":3},{"0":1,"e":3},{"0":1,"e":6},{"0":1,"e":3},{"0":1,"e":4}]}]},{"0":6,"c":6,"C":[{"0":6,"d":6,"E":[{"0":6,"e":6}]}],"D":[{"0":6,"d":6,"E":[{"0":6,"e":6}]}]}]},{"0":6,"b":12,"B":[{"0":6,"c":6,"C":[{"0":6,"d":172,"E":[{"0":6,"e":24},{"0":6,"e":12},{"0":6,"e":14},{"0":6,"e":13},{"0":6,"e":12},{"0":6,"e":12},{"0":6,"e":15},{"0":6,"e":14},{"0":6,"e":13},{"0":6,"e":12},{"0":6,"e":14},{"0":6,"e":16},{"0":6,"e":13},{"0":5,"e":12},{"0":5,"e":11},{"0":5,"e":11},{"0":5,"e":10},{"0":5,"e":14},{"0":5,"e":11},{"0":4,"e":8},{"0":4,"e":12},{"0":3,"e":6},{"0":3,"e":6},{"0":3,"e":6},{"0":3,"e":6},{"0":3,"e":6},{"0":3,"e":7},{"0":3,"e":6},{"0":3,"e":6},{"0":3,"e":7},{"0":3,"e":6},{"0":2,"e":4},{"0":2,"e":5},{"0":2,"e":4},{"0":2,"e":4},{"0":2,"e":4},{"0":2,"e":4},{"0":1,"e":2},{"0":1,"e":2},{"0":1,"e":3},{"0":1,"e":2},{"0":1,"e":2},{"0":1,"e":2},{"0":1,"e":2},{"0":1,"e":2},{"0":1,"e":2},{"0":1,"e":3},{"0":1,"e":2},{"0":1,"e":2},{"0":1,"e":2},{"0":1,"e":2}]}],"D":[{"0":6,"d":172,"E":[{"0":6,"e":30},{"0":6,"e":26},{"0":6,"e":28},{"0":6,"e":41},{"0":6,"e":28},{"0":6,"e":26},{"0":6,"e":40},{"0":6,"e":33},{"0":6,"e":29},{"0":6,"e":31},{"0":6,"e":35},{"0":6,"e":30},{"0":6,"e":39},{"0":5,"e":26},{"0":5,"e":27},{"0":5,"e":29},{"0":5,"e":22},{"0":5,"e":29},{"0":5,"e":27},{"0":4,"e":19},{"0":4,"e":32},{"0":3,"e":11},{"0":3,"e":17},{"0":3,"e":21},{"0":3,"e":16},{"0":3,"e":13},{"0":3,"e":17},{"0":3,"e":13},{"0":3,"e":16},{"0":3,"e":17},{"0":3,"e":13},{"0":2,"e":9},{"0":2,"e":11},{"0":2,"e":8},{"0":2,"e":8},{"0":2,"e":12},{"0":2,"e":20},{"0":1,"e":3},{"0":1,"e":6},{"0":1,"e":9},{"0":1,"e":4},{"0":1,"e":4},{"0":1,"e":5},{"0":1,"e":3},{"0":1,"e":5},{"0":1,"e":4},{"0":1,"e":6},{"0":1,"e":3},{"0":1,"e":6},{"0":1,"e":5},{"0":1,"e":6}]}]},{"0":6,"c":6,"C":[{"0":6,"d":6,"E":[{"0":6,"e":6}]}],"D":[{"0":6,"d":6,"E":[{"0":6,"e":6}]}]}]},{"0":6,"b":12,"B":[{"0":6,"c":6,"C":[{"0":6,"d":237,"E":[{"0":6,"e":24},{"0":6,"e":12},{"0":6,"e":12},{"0":6,"e":15},{"0":6,"e":12},{"0":6,"e":14},{"0":6,"e":13},{"0":6,"e":13},{"0":6,"e":13},{"0":6,"e":13},{"0":6,"e":14},{"0":6,"e":13},{"0":6,"e":14},{"0":6,"e":12},{"0":6,"e":12},{"0":6,"e":12},{"0":6,"e":14},{"0":5,"e":15},{"0":5,"e":13},{"0":5,"e":12},{"0":5,"e":10},{"0":5,"e":11},{"0":5,"e":13},{"0":5,"e":11},{"0":5,"e":11},{"0":5,"e":10},{"0":5,"e":10},{"0":5,"e":10},{"0":4,"e":10},{"0":4,"e":9},{"0":4,"e":10},{"0":4,"e":9},{"0":4,"e":8},{"0":4,"e":8},{"0":4,"e":9},{"0":4,"e":8},{"0":3,"e":6},{"0":3,"e":6},{"0":3,"e":6},{"0":3,"e":6},{"0":2,"e":5},{"0":2,"e":5},{"0":2,"e":6},{"0":2,"e":5},{"0":2,"e":4},{"0":2,"e":4},{"0":2,"e":4},{"0":2,"e":4},{"0":2,"e":5},{"0":2,"e":4},{"0":2,"e":4},{"0":2,"e":4},{"0":1,"e":2},{"0":1,"e":3},{"0":1,"e":2},{"0":1,"e":2},{"0":1,"e":2},{"0":1,"e":2},{"0":1,"e":2},{"0":1,"e":2},{"0":1,"e":2},{"0":1,"e":2},{"0":1,"e":2},{"0":1,"e":2}]}],"D":[{"0":6,"d":237,"E":[{"0":6,"e":30},{"0":6,"e":19},{"0":6,"e":27},{"0":6,"e":36},{"0":6,"e":35},{"0":6,"e":26},{"0":6,"e":29},{"0":6,"e":29},{"0":6,"e":28},{"0":6,"e":40},{"0":6,"e":36},{"0":6,"e":30},{"0":6,"e":32},{"0":6,"e":30},{"0":6,"e":24},{"0":6,"e":31},{"0":6,"e":34},{"0":5,"e":27},{"0":5,"e":30},{"0":5,"e":33},{"0":5,"e":21},{"0":5,"e":23},{"0":5,"e":40},{"0":5,"e":27},{"0":5,"e":23},{"0":5,"e":29},{"0":5,"e":22},{"0":5,"e":28},{"0":4,"e":32},{"0":4,"e":22},{"0":4,"e":18},{"0":4,"e":21},{"0":4,"e":26},{"0":4,"e":19},{"0":4,"e":24},{"0":4,"e":24},{"0":3,"e":18},{"0":3,"e":15},{"0":3,"e":19},{"0":3,"e":19},{"0":2,"e":9},{"0":2,"e":9},{"0":2,"e":16},{"0":2,"e":12},{"0":2,"e":9},{"0":2,"e":9},{"0":2,"e":11},{"0":2,"e":9},{"0":2,"e":10},{"0":2,"e":10},{"0":2,"e":7},{"0":2,"e":10},{"0":1,"e":6},{"0":1,"e":5},{"0":1,"e":4},{"0":1,"e":4},{"0":1,"e":6},{"0":1,"e":6},{"0":1,"e":3},{"0":1,"e":2},{"0":1,"e":6},{"0":1,"e":6},{"0":1,"e":4},{"0":1,"e":7}]}]},{"0":6,"c":6,"C":[{"0":6,"d":8,"E":[{"0":6,"e":10},{"0":1,"e":2},{"0":1,"e":7}]}],"D":[{"0":6,"d":8,"E":[{"0":6,"e":10},{"0":1,"e":5},{"0":1,"e":11}]}]}]},{"0":5,"b":10,"B":[{"0":5,"c":5,"C":[{"0":5,"d":121,"E":[{"0":5,"e":20},{"0":5,"e":10},{"0":5,"e":12},{"0":5,"e":11},{"0":5,"e":10},{"0":5,"e":10},{"0":5,"e":11},{"0":5,"e":14},{"0":5,"e":10},{"0":5,"e":10},{"0":5,"e":12},{"0":5,"e":12},{"0":5,"e":11},{"0":5,"e":13},{"0":5,"e":12},{"0":5,"e":11},{"0":5,"e":10},{"0":5,"e":10},{"0":5,"e":11},{"0":4,"e":9},{"0":3,"e":6},{"0":2,"e":4},{"0":2,"e":5},{"0":2,"e":5},{"0":2,"e":4},{"0":2,"e":4},{"0":1,"e":2},{"0":1,"e":2},{"0":1,"e":2},{"0":1,"e":2},{"0":1,"e":2},{"0":1,"e":2},{"0":1,"e":2},{"0":1,"e":2},{"0":1,"e":2}]}],"D":[{"0":5,"d":121,"E":[{"0":5,"e":25},{"0":5,"e":22},{"0":5,"e":21},{"0":5,"e":26},{"0":5,"e":30},{"0":5,"e":19},{"0":5,"e":23},{"0":5,"e":37},{"0":5,"e":24},{"0":5,"e":16},{"0":5,"e":30},{"0":5,"e":22},{"0":5,"e":30},{"0":5,"e":28},{"0":5,"e":24},{"0":5,"e":36},{"0":5,"e":25},{"0":5,"e":28},{"0":5,"e":39},{"0":4,"e":24},{"0":3,"e":22},{"0":2,"e":11},{"0":2,"e":14},{"0":2,"e":7},{"0":2,"e":10},{"0":2,"e":14},{"0":1,"e":5},{"0":1,"e":3},{"0":1,"e":8},{"0":1,"e":4},{"0":1,"e":4},{"0":1,"e":3},{"0":1,"e":6},{"0":1,"e":4},{"0":1,"e":7}]}]},{"0":5,"c":5,"C":[{"0":5,"d":5,"E":[{"0":5,"e":5}]}],"D":[{"0":5,"d":5,"E":[{"0":5,"e":5}]}]}]},{"0":5,"b":10,"B":[{"0":5,"c":5,"C":[{"0":5,"d":122,"E":[{"0":5,"e":20},{"0":5,"e":10},{"0":5,"e":12},{"0":5,"e":10},{"0":5,"e":10},{"0":5,"e":10},{"0":5,"e":13},{"0":5,"e":11},{"0":5,"e":10},{"0":5,"e":11},{"0":5,"e":10},{"0":5,"e":10},{"0":5,"e":12},{"0":5,"e":11},{"0":5,"e":11},{"0":5,"e":11},{"0":5,"e":11},{"0":4,"e":9},{"0":4,"e":9},{"0":4,"e":8},{"0":4,"e":8},{"0":2,"e":4},{"0":1,"e":2},{"0":1,"e":2},{"0":1,"e":2},{"0":1,"e":3},{"0":1,"e":2},{"0":1,"e":2},{"0":1,"e":2},{"0":1,"e":2},{"0":1,"e":2},{"0":1,"e":3},{"0":1,"e":2},{"0":1,"e":2},{"0":1,"e":2},{"0":1,"e":2},{"0":1,"e":2},{"0":1,"e":2},{"0":1,"e":2},{"0":1,"e":2},{"0":1,"e":2}]}],"D":[{"0":5,"d":122,"E":[{"0":5,"e":25},{"0":5,"e":15},{"0":5,"e":25},{"0":5,"e":19},{"0":5,"e":27},{"0":5,"e":19},{"0":5,"e":33},{"0":5,"e":27},{"0":5,"e":23},{"0":5,"e":38},{"0":5,"e":25},{"0":5,"e":25},{"0":5,"e":34},{"0":5,"e":24},{"0":5,"e":35},{"0":5,"e":30},{"0":5,"e":25},{"0":4,"e":27},{"0":4,"e":20},{"0":4,"e":23},{"0":4,"e":22},{"0":2,"e":9},{"0":1,"e":7},{"0":1,"e":3},{"0":1,"e":4},{"0":1,"e":7},{"0":1,"e":5},{"0":1,"e":7},{"0":1,"e":6},{"0":1,"e":4},{"0":1,"e":4},{"0":1,"e":8},{"0":1,"e":4},{"0":1,"e":5},{"0":1,"e":5},{"0":1,"e":5},{"0":1,"e":3},{"0":1,"e":3},{"0":1,"e":6},{"0":1,"e":3},{"0":1,"e":4}]}]},{"0":5,"c":5,"C":[{"0":5,"d":5,"E":[{"0":5,"e":5}]}],"D":[{"0":5,"d":5,"E":[{"0":5,"e":5}]}]}]},{"0":5,"b":10,"B":[{"0":5,"c":5,"C":[{"0":5,"d":132,"E":[{"0":5,"e":20},{"0":5,"e":10},{"0":5,"e":10},{"0":5,"e":11},{"0":5,"e":10},{"0":5,"e":10},{"0":5,"e":11},{"0":5,"e":12},{"0":5,"e":10},{"0":5,"e":11},{"0":5,"e":11},{"0":5,"e":12},{"0":5,"e":11},{"0":5,"e":12},{"0":5,"e":10},{"0":5,"e":11},{"0":5,"e":12},{"0":5,"e":11},{"0":5,"e":10},{"0":4,"e":8},{"0":4,"e":8},{"0":4,"e":8},{"0":3,"e":10},{"0":2,"e":4},{"0":2,"e":7},{"0":2,"e":4},{"0":2,"e":4},{"0":2,"e":4},{"0":2,"e":4},{"0":2,"e":4},{"0":2,"e":4},{"0":2,"e":4},{"0":2,"e":4},{"0":1,"e":2},{"0":1,"e":2}]}],"D":[{"0":5,"d":132,"E":[{"0":5,"e":25},{"0":5,"e":22},{"0":5,"e":25},{"0":5,"e":27},{"0":5,"e":27},{"0":5,"e":20},{"0":5,"e":33},{"0":5,"e":27},{"0":5,"e":26},{"0":5,"e":25},{"0":5,"e":25},{"0":5,"e":21},{"0":5,"e":29},{"0":5,"e":27},{"0":5,"e":28},{"0":5,"e":34},{"0":5,"e":28},{"0":5,"e":26},{"0":5,"e":33},{"0":4,"e":25},{"0":4,"e":17},{"0":4,"e":19},{"0":3,"e":26},{"0":2,"e":7},{"0":2,"e":11},{"0":2,"e":8},{"0":2,"e":9},{"0":2,"e":10},{"0":2,"e":10},{"0":2,"e":19},{"0":2,"e":8},{"0":2,"e":8},{"0":2,"e":17},{"0":1,"e":5},{"0":1,"e":4}]}]},{"0":5,"c":5,"C":[{"0":5,"d":7,"E":[{"0":5,"e":9},{"0":1,"e":2},{"0":1,"e":4}]}],"D":[{"0":5,"d":7,"E":[{"0":5,"e":9},{"0":1,"e":5},{"0":1,"e":10}]}]}]},{"0":5,"b":10,"B":[{"0":5,"c":5,"C":[{"0":5,"d":158,"E":[{"0":5,"e":20},{"0":5,"e":10},{"0":5,"e":10},{"0":5,"e":12},{"0":5,"e":11},{"0":5,"e":11},{"0":5,"e":11},{"0":5,"e":11},{"0":5,"e":12},{"0":5,"e":11},{"0":5,"e":11},{"0":5,"e":12},{"0":5,"e":11},{"0":5,"e":11},{"0":5,"e":10},{"0":5,"e":10},{"0":4,"e":9},{"0":4,"e":8},{"0":4,"e":9},{"0":4,"e":9},{"0":4,"e":12},{"0":4,"e":8},{"0":4,"e":9},{"0":4,"e":8},{"0":4,"e":8},{"0":4,"e":11},{"0":4,"e":8},{"0":4,"e":8},{"0":4,"e":9},{"0":4,"e":9},{"0":3,"e":6},{"0":3,"e":7},{"0":3,"e":6},{"0":3,"e":7},{"0":2,"e":4},{"0":2,"e":4},{"0":2,"e":4},{"0":1,"e":2},{"0":1,"e":2},{"0":1,"e":2},{"0":1,"e":2}]}],"D":[{"0":5,"d":158,"E":[{"0":5,"e":25},{"0":5,"e":19},{"0":5,"e":25},{"0":5,"e":25},{"0":5,"e":29},{"0":5,"e":26},{"0":5,"e":27},{"0":5,"e":23},{"0":5,"e":33},{"0":5,"e":34},{"0":5,"e":25},{"0":5,"e":27},{"0":5,"e":29},{"0":5,"e":37},{"0":5,"e":24},{"0":5,"e":27},{"0":4,"e":28},{"0":4,"e":17},{"0":4,"e":23},{"0":4,"e":41},{"0":4,"e":16},{"0":4,"e":16},{"0":4,"e":33},{"0":4,"e":21},{"0":4,"e":19},{"0":4,"e":32},{"0":4,"e":22},{"0":4,"e":20},{"0":4,"e":26},{"0":4,"e":27},{"0":3,"e":12},{"0":3,"e":16},{"0":3,"e":20},{"0":3,"e":22},{"0":2,"e":9},{"0":2,"e":13},{"0":2,"e":11},{"0":1,"e":3},{"0":1,"e":6},{"0":1,"e":3},{"0":1,"e":4}]}]},{"0":5,"c":5,"C":[{"0":5,"d":8,"E":[{"0":5,"e":11},{"0":1,"e":2},{"0":1,"e":6},{"0":1,"e":1}]}],"D":[{"0":5,"d":8,"E":[{"0":5,"e":11},{"0":1,"e":6},{"0":1,"e":9},{"0":1,"e":3}]}]}]},{"0":4,"b":8,"B":[{"0":4,"c":4,"C":[{"0":4,"d":135,"E":[{"0":4,"e":16},{"0":4,"e":8},{"0":4,"e":8},{"0":4,"e":10},{"0":4,"e":8},{"0":4,"e":8},{"0":4,"e":9},{"0":4,"e":10},{"0":4,"e":9},{"0":4,"e":9},{"0":4,"e":9},{"0":4,"e":9},{"0":4,"e":9},{"0":4,"e":10},{"0":4,"e":9},{"0":4,"e":8},{"0":4,"e":8},{"0":4,"e":10},{"0":4,"e":10},{"0":4,"e":9},{"0":4,"e":8},{"0":3,"e":7},{"0":3,"e":6},{"0":3,"e":6},{"0":3,"e":6},{"0":3,"e":6},{"0":3,"e":7},{"0":3,"e":6},{"0":3,"e":6},{"0":3,"e":6},{"0":3,"e":8},{"0":2,"e":4},{"0":2,"e":4},{"0":2,"e":4},{"0":2,"e":4},{"0":2,"e":4},{"0":2,"e":4},{"0":2,"e":4},{"0":2,"e":4},{"0":2,"e":4},{"0":2,"e":4},{"0":1,"e":2}]}],"D":[{"0":4,"d":135,"E":[{"0":4,"e":20},{"0":4,"e":16},{"0":4,"e":23},{"0":4,"e":23},{"0":4,"e":22},{"0":4,"e":16},{"0":4,"e":23},{"0":4,"e":26},{"0":4,"e":20},{"0":4,"e":19},{"0":4,"e":25},{"0":4,"e":21},{"0":4,"e":23},{"0":4,"e":20},{"0":4,"e":27},{"0":4,"e":17},{"0":4,"e":22},{"0":4,"e":31},{"0":4,"e":23},{"0":4,"e":18},{"0":4,"e":24},{"0":3,"e":28},{"0":3,"e":12},{"0":3,"e":19},{"0":3,"e":12},{"0":3,"e":15},{"0":3,"e":19},{"0":3,"e":22},{"0":3,"e":12},{"0":3,"e":15},{"0":3,"e":20},{"0":2,"e":10},{"0":2,"e":15},{"0":2,"e":13},{"0":2,"e":16},{"0":2,"e":9},{"0":2,"e":13},{"0":2,"e":11},{"0":2,"e":8},{"0":2,"e":14},{"0":2,"e":11},{"0":1,"e":6}]}]},{"0":4,"c":4,"C":[{"0":4,"d":4,"E":[{"0":4,"e":4}]}],"D":[{"0":4,"d":4,"E":[{"0":4,"e":4}]}]}]},{"0":4,"b":8,"B":[{"0":4,"c":4,"C":[{"0":4,"d":115,"E":[{"0":4,"e":16},{"0":4,"e":8},{"0":4,"e":10},{"0":4,"e":8},{"0":4,"e":10},{"0":4,"e":8},{"0":4,"e":9},{"0":4,"e":8},{"0":4,"e":8},{"0":4,"e":10},{"0":4,"e":8},{"0":4,"e":9},{"0":4,"e":10},{"0":4,"e":8},{"0":4,"e":10},{"0":4,"e":9},{"0":4,"e":8},{"0":3,"e":9},{"0":3,"e":7},{"0":3,"e":6},{"0":3,"e":6},{"0":3,"e":6},{"0":2,"e":4},{"0":2,"e":5},{"0":2,"e":4},{"0":2,"e":5},{"0":2,"e":4},{"0":2,"e":4},{"0":2,"e":4},{"0":2,"e":4},{"0":2,"e":4},{"0":2,"e":5},{"0":2,"e":4},{"0":2,"e":4},{"0":2,"e":4},{"0":1,"e":2},{"0":1,"e":2},{"0":1,"e":2},{"0":1,"e":2},{"0":1,"e":2},{"0":1,"e":2}]}],"D":[{"0":4,"d":115,"E":[{"0":4,"e":20},{"0":4,"e":13},{"0":4,"e":15},{"0":4,"e":23},{"0":4,"e":28},{"0":4,"e":14},{"0":4,"e":30},{"0":4,"e":21},{"0":4,"e":17},{"0":4,"e":36},{"0":4,"e":18},{"0":4,"e":21},{"0":4,"e":28},{"0":4,"e":20},{"0":4,"e":18},{"0":4,"e":30},{"0":4,"e":21},{"0":3,"e":21},{"0":3,"e":16},{"0":3,"e":23},{"0":3,"e":17},{"0":3,"e":14},{"0":2,"e":11},{"0":2,"e":17},{"0":2,"e":10},{"0":2,"e":11},{"0":2,"e":10},{"0":2,"e":10},{"0":2,"e":14},{"0":2,"e":8},{"0":2,"e":8},{"0":2,"e":11},{"0":2,"e":10},{"0":2,"e":9},{"0":2,"e":12},{"0":1,"e":5},{"0":1,"e":3},{"0":1,"e":3},{"0":1,"e":6},{"0":1,"e":3},{"0":1,"e":4}]}]},{"0":4,"c":4,"C":[{"0":4,"d":4,"E":[{"0":4,"e":4}]}],"D":[{"0":4,"d":4,"E":[{"0":4,"e":4}]}]}]},{"0":4,"b":8,"B":[{"0":4,"c":4,"C":[{"0":4,"d":115,"E":[{"0":4,"e":16},{"0":4,"e":8},{"0":4,"e":8},{"0":4,"e":8},{"0":4,"e":8},{"0":4,"e":8},{"0":4,"e":9},{"0":4,"e":11},{"0":4,"e":8},{"0":4,"e":8},{"0":4,"e":8},{"0":4,"e":8},{"0":4,"e":11},{"0":4,"e":10},{"0":4,"e":9},{"0":4,"e":9},{"0":4,"e":8},{"0":4,"e":8},{"0":4,"e":8},{"0":4,"e":8},{"0":4,"e":10},{"0":3,"e":7},{"0":3,"e":8},{"0":3,"e":6},{"0":3,"e":6},{"0":3,"e":7},{"0":3,"e":6},{"0":3,"e":6},{"0":1,"e":2},{"0":1,"e":2},{"0":1,"e":3},{"0":1,"e":2},{"0":1,"e":2},{"0":1,"e":2},{"0":1,"e":2},{"0":1,"e":2},{"0":1,"e":2},{"0":1,"e":2}]}],"D":[{"0":4,"d":115,"E":[{"0":4,"e":20},{"0":4,"e":16},{"0":4,"e":19},{"0":4,"e":25},{"0":4,"e":21},{"0":4,"e":25},{"0":4,"e":17},{"0":4,"e":27},{"0":4,"e":22},{"0":4,"e":14},{"0":4,"e":19},{"0":4,"e":27},{"0":4,"e":29},{"0":4,"e":25},{"0":4,"e":22},{"0":4,"e":17},{"0":4,"e":19},{"0":4,"e":30},{"0":4,"e":19},{"0":4,"e":21},{"0":4,"e":33},{"0":3,"e":16},{"0":3,"e":16},{"0":3,"e":13},{"0":3,"e":19},{"0":3,"e":16},{"0":3,"e":16},{"0":3,"e":20},{"0":1,"e":6},{"0":1,"e":6},{"0":1,"e":10},{"0":1,"e":10},{"0":1,"e":3},{"0":1,"e":4},{"0":1,"e":6},{"0":1,"e":3},{"0":1,"e":6},{"0":1,"e":8}]}]},{"0":4,"c":4,"C":[{"0":4,"d":4,"E":[{"0":4,"e":4}]}],"D":[{"0":4,"d":4,"E":[{"0":4,"e":4}]}]}]},{"0":3,"b":6,"B":[{"0":3,"c":3,"C":[{"0":3,"d":100,"E":[{"0":3,"e":12},{"0":3,"e":6},{"0":3,"e":6},{"0":3,"e":6},{"0":3,"e":6},{"0":3,"e":6},{"0":3,"e":7},{"0":3,"e":6},{"0":3,"e":6},{"0":3,"e":7},{"0":3,"e":6},{"0":3,"e":7},{"0":3,"e":7},{"0":3,"e":6},{"0":3,"e":6},{"0":3,"e":8},{"0":3,"e":6},{"0":3,"e":6},{"0":3,"e":8},{"0":3,"e":6},{"0":3,"e":7},{"0":3,"e":8},{"0":3,"e":6},{"0":3,"e":6},{"0":3,"e":6},{"0":3,"e":7},{"0":3,"e":6},{"0":3,"e":6},{"0":2,"e":4},{"0":2,"e":4},{"0":2,"e":4},{"0":1,"e":3},{"0":1,"e":2},{"0":1,"e":2},{"0":1,"e":2},{"0":1,"e":2},{"0":1,"e":2},{"0":1,"e":2},{"0":1,"e":2},{"0":1,"e":2},{"0":1,"e":2}]}],"D":[{"0":3,"d":100,"E":[{"0":3,"e":15},{"0":3,"e":11},{"0":3,"e":14},{"0":3,"e":16},{"0":3,"e":16},{"0":3,"e":11},{"0":3,"e":22},{"0":3,"e":11},{"0":3,"e":15},{"0":3,"e":26},{"0":3,"e":15},{"0":3,"e":15},{"0":3,"e":25},{"0":3,"e":10},{"0":3,"e":16},{"0":3,"e":21},{"0":3,"e":15},{"0":3,"e":14},{"0":3,"e":22},{"0":3,"e":17},{"0":3,"e":16},{"0":3,"e":17},{"0":3,"e":16},{"0":3,"e":13},{"0":3,"e":18},{"0":3,"e":14},{"0":3,"e":14},{"0":3,"e":23},{"0":2,"e":10},{"0":2,"e":15},{"0":2,"e":14},{"0":1,"e":8},{"0":1,"e":4},{"0":1,"e":5},{"0":1,"e":5},{"0":1,"e":5},{"0":1,"e":3},{"0":1,"e":3},{"0":1,"e":6},{"0":1,"e":3},{"0":1,"e":4}]}]},{"0":3,"c":3,"C":[{"0":3,"d":3,"E":[{"0":3,"e":3}]}],"D":[{"0":3,"d":3,"E":[{"0":3,"e":3}]}]}]},{"0":3,"b":6,"B":[{"0":3,"c":3,"C":[{"0":3,"d":80,"E":[{"0":3,"e":12},{"0":3,"e":6},{"0":3,"e":11},{"0":3,"e":6},{"0":3,"e":6},{"0":3,"e":6},{"0":3,"e":7},{"0":3,"e":8},{"0":3,"e":6},{"0":3,"e":6},{"0":3,"e":6},{"0":3,"e":6},{"0":3,"e":8},{"0":3,"e":9},{"0":3,"e":6},{"0":3,"e":6},{"0":3,"e":6},{"0":3,"e":6},{"0":2,"e":5},{"0":2,"e":4},{"0":2,"e":4},{"0":1,"e":2},{"0":1,"e":3},{"0":1,"e":2},{"0":1,"e":2},{"0":1,"e":2},{"0":1,"e":3},{"0":1,"e":2},{"0":1,"e":2},{"0":1,"e":2},{"0":1,"e":3},{"0":1,"e":2},{"0":1,"e":2},{"0":1,"e":2},{"0":1,"e":2},{"0":1,"e":3},{"0":1,"e":2},{"0":1,"e":2},{"0":1,"e":2},{"0":1,"e":2},{"0":1,"e":2}]}],"D":[{"0":3,"d":80,"E":[{"0":3,"e":15},{"0":3,"e":14},{"0":3,"e":22},{"0":3,"e":14},{"0":3,"e":22},{"0":3,"e":16},{"0":3,"e":16},{"0":3,"e":15},{"0":3,"e":10},{"0":3,"e":15},{"0":3,"e":18},{"0":3,"e":15},{"0":3,"e":20},{"0":3,"e":20},{"0":3,"e":16},{"0":3,"e":19},{"0":3,"e":13},{"0":3,"e":19},{"0":2,"e":16},{"0":2,"e":9},{"0":2,"e":12},{"0":1,"e":5},{"0":1,"e":9},{"0":1,"e":4},{"0":1,"e":4},{"0":1,"e":8},{"0":1,"e":9},{"0":1,"e":4},{"0":1,"e":4},{"0":1,"e":8},{"0":1,"e":9},{"0":1,"e":4},{"0":1,"e":4},{"0":1,"e":4},{"0":1,"e":8},{"0":1,"e":9},{"0":1,"e":4},{"0":1,"e":4},{"0":1,"e":5},{"0":1,"e":8},{"0":1,"e":8}]}]},{"0":3,"c":3,"C":[{"0":3,"d":9,"E":[{"0":3,"e":7},{"0":1,"e":2},{"0":1,"e":3},{"0":1,"e":2},{"0":1,"e":2},{"0":1,"e":2},{"0":1,"e":6}]}],"D":[{"0":3,"d":9,"E":[{"0":3,"e":7},{"0":1,"e":5},{"0":1,"e":5},{"0":1,"e":7},{"0":1,"e":3},{"0":1,"e":4},{"0":1,"e":11}]}]}]},{"0":3,"b":6,"B":[{"0":3,"c":3,"C":[{"0":3,"d":108,"E":[{"0":3,"e":12},{"0":3,"e":6},{"0":3,"e":8},{"0":3,"e":6},{"0":3,"e":6},{"0":3,"e":6},{"0":3,"e":7},{"0":3,"e":11},{"0":3,"e":9},{"0":3,"e":7},{"0":3,"e":6},{"0":3,"e":7},{"0":3,"e":7},{"0":3,"e":7},{"0":3,"e":7},{"0":3,"e":6},{"0":3,"e":7},{"0":3,"e":6},{"0":2,"e":4},{"0":2,"e":5},{"0":2,"e":4},{"0":2,"e":4},{"0":2,"e":4},{"0":2,"e":5},{"0":2,"e":4},{"0":2,"e":5},{"0":2,"e":4},{"0":2,"e":4},{"0":2,"e":4},{"0":2,"e":4},{"0":2,"e":4},{"0":2,"e":4},{"0":2,"e":5},{"0":2,"e":4},{"0":2,"e":4},{"0":2,"e":4},{"0":2,"e":6},{"0":2,"e":4},{"0":2,"e":5},{"0":2,"e":4},{"0":2,"e":4},{"0":2,"e":4},{"0":1,"e":2},{"0":1,"e":2},{"0":1,"e":2},{"0":1,"e":2},{"0":1,"e":2},{"0":1,"e":2}]}],"D":[{"0":3,"d":108,"E":[{"0":3,"e":15},{"0":3,"e":12},{"0":3,"e":14},{"0":3,"e":17},{"0":3,"e":17},{"0":3,"e":12},{"0":3,"e":23},{"0":3,"e":21},{"0":3,"e":15},{"0":3,"e":17},{"0":3,"e":13},{"0":3,"e":22},{"0":3,"e":19},{"0":3,"e":19},{"0":3,"e":14},{"0":3,"e":16},{"0":3,"e":22},{"0":3,"e":20},{"0":2,"e":9},{"0":2,"e":14},{"0":2,"e":14},{"0":2,"e":7},{"0":2,"e":10},{"0":2,"e":17},{"0":2,"e":12},{"0":2,"e":15},{"0":2,"e":14},{"0":2,"e":9},{"0":2,"e":8},{"0":2,"e":14},{"0":2,"e":13},{"0":2,"e":7},{"0":2,"e":11},{"0":2,"e":17},{"0":2,"e":10},{"0":2,"e":10},{"0":2,"e":11},{"0":2,"e":7},{"0":2,"e":12},{"0":2,"e":9},{"0":2,"e":8},{"0":2,"e":11},{"0":1,"e":5},{"0":1,"e":3},{"0":1,"e":3},{"0":1,"e":6},{"0":1,"e":3},{"0":1,"e":4}]}]},{"0":3,"c":3,"C":[{"0":3,"d":3,"E":[{"0":3,"e":3}]}],"D":[{"0":3,"d":3,"E":[{"0":3,"e":3}]}]}]},{"0":3,"b":6,"B":[{"0":3,"c":3,"C":[{"0":3,"d":93,"E":[{"0":3,"e":12},{"0":3,"e":6},{"0":3,"e":6},{"0":3,"e":6},{"0":3,"e":6},{"0":3,"e":6},{"0":3,"e":7},{"0":3,"e":8},{"0":3,"e":6},{"0":3,"e":6},{"0":3,"e":7},{"0":3,"e":7},{"0":3,"e":9},{"0":3,"e":9},{"0":3,"e":6},{"0":3,"e":6},{"0":3,"e":6},{"0":3,"e":6},{"0":3,"e":6},{"0":2,"e":5},{"0":2,"e":5},{"0":1,"e":3},{"0":1,"e":3},{"0":1,"e":2},{"0":1,"e":2},{"0":1,"e":2},{"0":1,"e":2},{"0":1,"e":3},{"0":1,"e":2},{"0":1,"e":2},{"0":1,"e":2},{"0":1,"e":2},{"0":1,"e":2},{"0":1,"e":2},{"0":1,"e":2},{"0":1,"e":2},{"0":1,"e":2},{"0":1,"e":2},{"0":1,"e":2},{"0":1,"e":2},{"0":1,"e":2},{"0":1,"e":3},{"0":1,"e":2},{"0":1,"e":2},{"0":1,"e":2},{"0":1,"e":2},{"0":1,"e":2},{"0":1,"e":2},{"0":1,"e":2},{"0":1,"e":2},{"0":1,"e":2},{"0":1,"e":2},{"0":1,"e":2}]}],"D":[{"0":3,"d":93,"E":[{"0":3,"e":15},{"0":3,"e":12},{"0":3,"e":15},{"0":3,"e":16},{"0":3,"e":19},{"0":3,"e":19},{"0":3,"e":16},{"0":3,"e":15},{"0":3,"e":19},{"0":3,"e":14},{"0":3,"e":19},{"0":3,"e":20},{"0":3,"e":22},{"0":3,"e":24},{"0":3,"e":14},{"0":3,"e":23},{"0":3,"e":11},{"0":3,"e":15},{"0":3,"e":24},{"0":2,"e":16},{"0":2,"e":15},{"0":1,"e":4},{"0":1,"e":7},{"0":1,"e":4},{"0":1,"e":6},{"0":1,"e":4},{"0":1,"e":4},{"0":1,"e":6},{"0":1,"e":8},{"0":1,"e":4},{"0":1,"e":7},{"0":1,"e":3},{"0":1,"e":4},{"0":1,"e":10},{"0":1,"e":4},{"0":1,"e":4},{"0":1,"e":7},{"0":1,"e":3},{"0":1,"e":4},{"0":1,"e":9},{"0":1,"e":3},{"0":1,"e":8},{"0":1,"e":4},{"0":1,"e":4},{"0":1,"e":9},{"0":1,"e":5},{"0":1,"e":7},{"0":1,"e":5},{"0":1,"e":6},{"0":1,"e":3},{"0":1,"e":4},{"0":1,"e":3},{"0":1,"e":6}]}]},{"0":3,"c":3,"C":[{"0":3,"d":3,"E":[{"0":3,"e":3}]}],"D":[{"0":3,"d":3,"E":[{"0":3,"e":3}]}]}]},{"0":3,"b":6,"B":[{"0":3,"c":3,"C":[{"0":3,"d":105,"E":[{"0":3,"e":12},{"0":3,"e":6},{"0":3,"e":6},{"0":3,"e":6},{"0":3,"e":6},{"0":3,"e":6},{"0":3,"e":7},{"0":3,"e":7},{"0":3,"e":6},{"0":3,"e":7},{"0":3,"e":6},{"0":3,"e":7},{"0":3,"e":7},{"0":3,"e":6},{"0":3,"e":6},{"0":3,"e":6},{"0":3,"e":6},{"0":3,"e":6},{"0":3,"e":11},{"0":3,"e":6},{"0":3,"e":6},{"0":3,"e":7},{"0":3,"e":6},{"0":3,"e":6},{"0":3,"e":6},{"0":3,"e":7},{"0":3,"e":6},{"0":3,"e":6},{"0":2,"e":4},{"0":2,"e":4},{"0":2,"e":5},{"0":2,"e":7},{"0":2,"e":4},{"0":2,"e":4},{"0":2,"e":4},{"0":2,"e":4},{"0":1,"e":2},{"0":1,"e":2},{"0":1,"e":2},{"0":1,"e":2},{"0":1,"e":2}]}],"D":[{"0":3,"d":105,"E":[{"0":3,"e":15},{"0":3,"e":11},{"0":3,"e":15},{"0":3,"e":15},{"0":3,"e":22},{"0":3,"e":10},{"0":3,"e":21},{"0":3,"e":17},{"0":3,"e":17},{"0":3,"e":25},{"0":3,"e":16},{"0":3,"e":17},{"0":3,"e":25},{"0":3,"e":10},{"0":3,"e":13},{"0":3,"e":27},{"0":3,"e":11},{"0":3,"e":14},{"0":3,"e":26},{"0":3,"e":25},{"0":3,"e":13},{"0":3,"e":19},{"0":3,"e":14},{"0":3,"e":11},{"0":3,"e":21},{"0":3,"e":15},{"0":3,"e":11},{"0":3,"e":26},{"0":2,"e":10},{"0":2,"e":8},{"0":2,"e":12},{"0":2,"e":15},{"0":2,"e":11},{"0":2,"e":9},{"0":2,"e":9},{"0":2,"e":14},{"0":1,"e":3},{"0":1,"e":3},{"0":1,"e":6},{"0":1,"e":3},{"0":1,"e":4}]}]},{"0":3,"c":3,"C":[{"0":3,"d":3,"E":[{"0":3,"e":3}]}],"D":[{"0":3,"d":3,"E":[{"0":3,"e":3}]}]}]},{"0":3,"b":6,"B":[{"0":3,"c":3,"C":[{"0":3,"d":79,"E":[{"0":3,"e":12},{"0":3,"e":6},{"0":3,"e":6},{"0":3,"e":6},{"0":3,"e":8},{"0":3,"e":6},{"0":3,"e":7},{"0":3,"e":10},{"0":3,"e":6},{"0":3,"e":6},{"0":3,"e":7},{"0":3,"e":6},{"0":3,"e":7},{"0":3,"e":8},{"0":3,"e":6},{"0":3,"e":6},{"0":3,"e":7},{"0":3,"e":6},{"0":3,"e":6},{"0":3,"e":6},{"0":3,"e":6},{"0":2,"e":4},{"0":2,"e":4},{"0":2,"e":4},{"0":2,"e":4},{"0":1,"e":3},{"0":1,"e":2},{"0":1,"e":2},{"0":1,"e":2},{"0":1,"e":2},{"0":1,"e":2},{"0":1,"e":2},{"0":1,"e":2}]}],"D":[{"0":3,"d":79,"E":[{"0":3,"e":15},{"0":3,"e":13},{"0":3,"e":15},{"0":3,"e":14},{"0":3,"e":21},{"0":3,"e":17},{"0":3,"e":14},{"0":3,"e":20},{"0":3,"e":21},{"0":3,"e":14},{"0":3,"e":20},{"0":3,"e":16},{"0":3,"e":17},{"0":3,"e":17},{"0":3,"e":16},{"0":3,"e":13},{"0":3,"e":17},{"0":3,"e":23},{"0":3,"e":11},{"0":3,"e":20},{"0":3,"e":17},{"0":2,"e":6},{"0":2,"e":14},{"0":2,"e":8},{"0":2,"e":11},{"0":1,"e":8},{"0":1,"e":4},{"0":1,"e":5},{"0":1,"e":4},{"0":1,"e":7},{"0":1,"e":3},{"0":1,"e":6},{"0":1,"e":6}]}]},{"0":3,"c":3,"C":[{"0":3,"d":3,"E":[{"0":3,"e":3}]}],"D":[{"0":3,"d":3,"E":[{"0":3,"e":3}]}]}]},{"0":3,"b":6,"B":[{"0":3,"c":3,"C":[{"0":3,"d":123,"E":[{"0":3,"e":12},{"0":3,"e":6},{"0":3,"e":8},{"0":3,"e":6},{"0":3,"e":6},{"0":3,"e":6},{"0":3,"e":7},{"0":3,"e":6},{"0":3,"e":6},{"0":3,"e":8},{"0":3,"e":8},{"0":3,"e":6},{"0":3,"e":10},{"0":3,"e":6},{"0":3,"e":7},{"0":3,"e":6},{"0":3,"e":6},{"0":3,"e":6},{"0":3,"e":7},{"0":3,"e":6},{"0":3,"e":6},{"0":3,"e":6},{"0":3,"e":7},{"0":3,"e":6},{"0":3,"e":6},{"0":3,"e":7},{"0":3,"e":7},{"0":3,"e":6},{"0":3,"e":6},{"0":3,"e":6},{"0":3,"e":6},{"0":3,"e":7},{"0":3,"e":6},{"0":3,"e":6},{"0":3,"e":6},{"0":3,"e":6},{"0":3,"e":6},{"0":3,"e":6},{"0":3,"e":6},{"0":3,"e":8},{"0":2,"e":4},{"0":1,"e":2}]}],"D":[{"0":3,"d":123,"E":[{"0":3,"e":15},{"0":3,"e":12},{"0":3,"e":14},{"0":3,"e":15},{"0":3,"e":19},{"0":3,"e":12},{"0":3,"e":27},{"0":3,"e":10},{"0":3,"e":13},{"0":3,"e":25},{"0":3,"e":14},{"0":3,"e":14},{"0":3,"e":23},{"0":3,"e":14},{"0":3,"e":16},{"0":3,"e":13},{"0":3,"e":11},{"0":3,"e":21},{"0":3,"e":21},{"0":3,"e":17},{"0":3,"e":20},{"0":3,"e":10},{"0":3,"e":19},{"0":3,"e":18},{"0":3,"e":11},{"0":3,"e":18},{"0":3,"e":22},{"0":3,"e":16},{"0":3,"e":20},{"0":3,"e":16},{"0":3,"e":13},{"0":3,"e":16},{"0":3,"e":15},{"0":3,"e":26},{"0":3,"e":14},{"0":3,"e":13},{"0":3,"e":22},{"0":3,"e":9},{"0":3,"e":14},{"0":3,"e":19},{"0":2,"e":7},{"0":1,"e":7}]}]},{"0":3,"c":3,"C":[{"0":3,"d":3,"E":[{"0":3,"e":3}]}],"D":[{"0":3,"d":3,"E":[{"0":3,"e":3}]}]}]},{"0":3,"b":6,"B":[{"0":3,"c":3,"C":[{"0":3,"d":62,"E":[{"0":3,"e":12},{"0":3,"e":6},{"0":3,"e":6},{"0":3,"e":7},{"0":3,"e":6},{"0":3,"e":6},{"0":3,"e":9},{"0":3,"e":8},{"0":3,"e":7},{"0":3,"e":6},{"0":3,"e":6},{"0":3,"e":6},{"0":3,"e":7},{"0":3,"e":8},{"0":3,"e":7},{"0":3,"e":6},{"0":3,"e":6},{"0":2,"e":5},{"0":2,"e":4},{"0":2,"e":4},{"0":2,"e":4},{"0":1,"e":2},{"0":1,"e":2},{"0":1,"e":2}]}],"D":[{"0":3,"d":62,"E":[{"0":3,"e":15},{"0":3,"e":12},{"0":3,"e":15},{"0":3,"e":21},{"0":3,"e":17},{"0":3,"e":12},{"0":3,"e":22},{"0":3,"e":20},{"0":3,"e":12},{"0":3,"e":17},{"0":3,"e":13},{"0":3,"e":17},{"0":3,"e":21},{"0":3,"e":14},{"0":3,"e":24},{"0":3,"e":18},{"0":3,"e":18},{"0":2,"e":19},{"0":2,"e":7},{"0":2,"e":9},{"0":2,"e":14},{"0":1,"e":3},{"0":1,"e":6},{"0":1,"e":8}]}]},{"0":3,"c":3,"C":[{"0":3,"d":3,"E":[{"0":3,"e":3}]}],"D":[{"0":3,"d":3,"E":[{"0":3,"e":3}]}]}]},{"0":3,"b":6,"B":[{"0":3,"c":3,"C":[{"0":3,"d":104,"E":[{"0":3,"e":12},{"0":3,"e":6},{"0":3,"e":6},{"0":3,"e":6},{"0":3,"e":6},{"0":3,"e":6},{"0":3,"e":7},{"0":3,"e":6},{"0":3,"e":6},{"0":3,"e":7},{"0":3,"e":7},{"0":3,"e":7},{"0":3,"e":7},{"0":3,"e":6},{"0":3,"e":6},{"0":3,"e":6},{"0":3,"e":7},{"0":3,"e":6},{"0":3,"e":8},{"0":3,"e":6},{"0":3,"e":6},{"0":3,"e":6},{"0":3,"e":6},{"0":3,"e":7},{"0":3,"e":6},{"0":3,"e":7},{"0":3,"e":6},{"0":3,"e":6},{"0":2,"e":4},{"0":2,"e":4},{"0":2,"e":4},{"0":2,"e":5},{"0":2,"e":4},{"0":2,"e":4},{"0":2,"e":4},{"0":1,"e":2},{"0":1,"e":2},{"0":1,"e":2},{"0":1,"e":2},{"0":1,"e":2},{"0":1,"e":2}]}],"D":[{"0":3,"d":104,"E":[{"0":3,"e":15},{"0":3,"e":11},{"0":3,"e":14},{"0":3,"e":14},{"0":3,"e":23},{"0":3,"e":13},{"0":3,"e":15},{"0":3,"e":12},{"0":3,"e":18},{"0":3,"e":22},{"0":3,"e":19},{"0":3,"e":16},{"0":3,"e":18},{"0":3,"e":13},{"0":3,"e":13},{"0":3,"e":19},{"0":3,"e":16},{"0":3,"e":13},{"0":3,"e":24},{"0":3,"e":19},{"0":3,"e":12},{"0":3,"e":18},{"0":3,"e":13},{"0":3,"e":13},{"0":3,"e":20},{"0":3,"e":17},{"0":3,"e":13},{"0":3,"e":24},{"0":2,"e":15},{"0":2,"e":8},{"0":2,"e":12},{"0":2,"e":12},{"0":2,"e":15},{"0":2,"e":9},{"0":2,"e":14},{"0":1,"e":5},{"0":1,"e":3},{"0":1,"e":3},{"0":1,"e":6},{"0":1,"e":3},{"0":1,"e":4}]}]},{"0":3,"c":3,"C":[{"0":3,"d":3,"E":[{"0":3,"e":3}]}],"D":[{"0":3,"d":3,"E":[{"0":3,"e":3}]}]}]},{"0":3,"b":6,"B":[{"0":3,"c":3,"C":[{"0":3,"d":47,"E":[{"0":3,"e":12},{"0":3,"e":6},{"0":3,"e":6},{"0":3,"e":6},{"0":3,"e":8},{"0":3,"e":6},{"0":3,"e":7},{"0":3,"e":9},{"0":3,"e":6},{"0":2,"e":4},{"0":2,"e":5},{"0":2,"e":4},{"0":2,"e":5},{"0":2,"e":6},{"0":2,"e":4},{"0":2,"e":4},{"0":2,"e":4},{"0":1,"e":2},{"0":1,"e":2},{"0":1,"e":2},{"0":1,"e":2}]}],"D":[{"0":3,"d":47,"E":[{"0":3,"e":15},{"0":3,"e":13},{"0":3,"e":15},{"0":3,"e":14},{"0":3,"e":21},{"0":3,"e":18},{"0":3,"e":14},{"0":3,"e":19},{"0":3,"e":16},{"0":2,"e":10},{"0":2,"e":16},{"0":2,"e":8},{"0":2,"e":11},{"0":2,"e":16},{"0":2,"e":15},{"0":2,"e":8},{"0":2,"e":12},{"0":1,"e":9},{"0":1,"e":4},{"0":1,"e":6},{"0":1,"e":8}]}]},{"0":3,"c":3,"C":[{"0":3,"d":3,"E":[{"0":3,"e":3}]}],"D":[{"0":3,"d":3,"E":[{"0":3,"e":3}]}]}]},{"0":3,"b":6,"B":[{"0":3,"c":3,"C":[{"0":3,"d":107,"E":[{"0":3,"e":12},{"0":3,"e":6},{"0":3,"e":8},{"0":3,"e":6},{"0":3,"e":6},{"0":3,"e":6},{"0":3,"e":7},{"0":3,"e":6},{"0":3,"e":6},{"0":3,"e":7},{"0":3,"e":6},{"0":3,"e":6},{"0":3,"e":7},{"0":3,"e":7},{"0":3,"e":7},{"0":3,"e":6},{"0":3,"e":6},{"0":3,"e":6},{"0":3,"e":7},{"0":3,"e":6},{"0":3,"e":6},{"0":3,"e":6},{"0":3,"e":6},{"0":3,"e":7},{"0":3,"e":6},{"0":3,"e":7},{"0":3,"e":8},{"0":3,"e":6},{"0":3,"e":6},{"0":3,"e":7},{"0":3,"e":6},{"0":3,"e":9},{"0":2,"e":4},{"0":2,"e":6},{"0":1,"e":2},{"0":1,"e":2},{"0":1,"e":2},{"0":1,"e":2},{"0":1,"e":2},{"0":1,"e":2},{"0":1,"e":2}]}],"D":[{"0":3,"d":107,"E":[{"0":3,"e":15},{"0":3,"e":13},{"0":3,"e":12},{"0":3,"e":18},{"0":3,"e":22},{"0":3,"e":11},{"0":3,"e":20},{"0":3,"e":10},{"0":3,"e":20},{"0":3,"e":28},{"0":3,"e":13},{"0":3,"e":19},{"0":3,"e":18},{"0":3,"e":14},{"0":3,"e":16},{"0":3,"e":15},{"0":3,"e":16},{"0":3,"e":13},{"0":3,"e":19},{"0":3,"e":27},{"0":3,"e":21},{"0":3,"e":10},{"0":3,"e":17},{"0":3,"e":16},{"0":3,"e":11},{"0":3,"e":15},{"0":3,"e":20},{"0":3,"e":16},{"0":3,"e":13},{"0":3,"e":15},{"0":3,"e":9},{"0":3,"e":19},{"0":2,"e":8},{"0":2,"e":12},{"0":1,"e":5},{"0":1,"e":5},{"0":1,"e":3},{"0":1,"e":3},{"0":1,"e":6},{"0":1,"e":3},{"0":1,"e":4}]}]},{"0":3,"c":3,"C":[{"0":3,"d":3,"E":[{"0":3,"e":3}]}],"D":[{"0":3,"d":3,"E":[{"0":3,"e":3}]}]}]},{"0":3,"b":6,"B":[{"0":3,"c":3,"C":[{"0":3,"d":81,"E":[{"0":3,"e":12},{"0":3,"e":6},{"0":3,"e":6},{"0":3,"e":6},{"0":3,"e":6},{"0":3,"e":6},{"0":3,"e":7},{"0":3,"e":8},{"0":3,"e":7},{"0":3,"e":6},{"0":3,"e":6},{"0":3,"e":6},{"0":3,"e":7},{"0":3,"e":8},{"0":3,"e":6},{"0":3,"e":6},{"0":3,"e":6},{"0":3,"e":6},{"0":3,"e":7},{"0":3,"e":6},{"0":3,"e":6},{"0":2,"e":5},{"0":2,"e":4},{"0":2,"e":4},{"0":2,"e":5},{"0":2,"e":4},{"0":2,"e":4},{"0":2,"e":4},{"0":2,"e":4},{"0":1,"e":2},{"0":1,"e":2}]}],"D":[{"0":3,"d":81,"E":[{"0":3,"e":15},{"0":3,"e":14},{"0":3,"e":15},{"0":3,"e":16},{"0":3,"e":19},{"0":3,"e":16},{"0":3,"e":12},{"0":3,"e":14},{"0":3,"e":21},{"0":3,"e":12},{"0":3,"e":16},{"0":3,"e":11},{"0":3,"e":21},{"0":3,"e":15},{"0":3,"e":21},{"0":3,"e":14},{"0":3,"e":16},{"0":3,"e":19},{"0":3,"e":18},{"0":3,"e":21},{"0":3,"e":17},{"0":2,"e":14},{"0":2,"e":13},{"0":2,"e":9},{"0":2,"e":12},{"0":2,"e":12},{"0":2,"e":7},{"0":2,"e":11},{"0":2,"e":13},{"0":1,"e":4},{"0":1,"e":8}]}]},{"0":3,"c":3,"C":[{"0":3,"d":3,"E":[{"0":3,"e":3}]}],"D":[{"0":3,"d":3,"E":[{"0":3,"e":3}]}]}]},{"0":3,"b":6,"B":[{"0":3,"c":3,"C":[{"0":3,"d":104,"E":[{"0":3,"e":12},{"0":3,"e":6},{"0":3,"e":6},{"0":3,"e":6},{"0":3,"e":6},{"0":3,"e":6},{"0":3,"e":7},{"0":3,"e":6},{"0":3,"e":6},{"0":3,"e":7},{"0":3,"e":7},{"0":3,"e":7},{"0":3,"e":7},{"0":3,"e":6},{"0":3,"e":6},{"0":3,"e":6},{"0":3,"e":6},{"0":3,"e":6},{"0":3,"e":7},{"0":3,"e":6},{"0":3,"e":10},{"0":3,"e":9},{"0":3,"e":14},{"0":3,"e":6},{"0":3,"e":6},{"0":3,"e":9},{"0":3,"e":6},{"0":3,"e":6},{"0":2,"e":4},{"0":2,"e":4},{"0":2,"e":4},{"0":2,"e":5},{"0":2,"e":4},{"0":2,"e":4},{"0":2,"e":4},{"0":1,"e":2},{"0":1,"e":2},{"0":1,"e":2},{"0":1,"e":2},{"0":1,"e":2},{"0":1,"e":2}]}],"D":[{"0":3,"d":104,"E":[{"0":3,"e":15},{"0":3,"e":12},{"0":3,"e":16},{"0":3,"e":15},{"0":3,"e":18},{"0":3,"e":12},{"0":3,"e":25},{"0":3,"e":23},{"0":3,"e":14},{"0":3,"e":23},{"0":3,"e":18},{"0":3,"e":17},{"0":3,"e":20},{"0":3,"e":14},{"0":3,"e":12},{"0":3,"e":15},{"0":3,"e":16},{"0":3,"e":15},{"0":3,"e":18},{"0":3,"e":23},{"0":3,"e":15},{"0":3,"e":13},{"0":3,"e":26},{"0":3,"e":11},{"0":3,"e":15},{"0":3,"e":20},{"0":3,"e":15},{"0":3,"e":19},{"0":2,"e":13},{"0":2,"e":7},{"0":2,"e":8},{"0":2,"e":19},{"0":2,"e":7},{"0":2,"e":9},{"0":2,"e":18},{"0":1,"e":5},{"0":1,"e":3},{"0":1,"e":3},{"0":1,"e":6},{"0":1,"e":3},{"0":1,"e":4}]}]},{"0":3,"c":6,"C":[{"0":3,"d":6,"E":[{"0":3,"e":9},{"0":1,"e":2},{"0":1,"e":2},{"0":1,"e":5}]},{"0":1,"d":3,"E":[{"0":1,"e":7},{"0":1,"e":2},{"0":1,"e":1}]},{"0":1,"d":3,"E":[{"0":1,"e":3},{"0":1,"e":2},{"0":1,"e":5}]},{"0":1,"d":3,"E":[{"0":1,"e":3},{"0":1,"e":2},{"0":1,"e":5}]}],"D":[{"0":3,"d":6,"E":[{"0":3,"e":9},{"0":1,"e":6},{"0":1,"e":4},{"0":1,"e":9}]},{"0":1,"d":3,"E":[{"0":1,"e":13},{"0":1,"e":4},{"0":1,"e":3}]},{"0":1,"d":3,"E":[{"0":1,"e":7},{"0":1,"e":4},{"0":1,"e":8}]},{"0":1,"d":3,"E":[{"0":1,"e":7},{"0":1,"e":4},{"0":1,"e":8}]}]}]},{"0":3,"b":6,"B":[{"0":3,"c":3,"C":[{"0":3,"d":60,"E":[{"0":3,"e":12},{"0":3,"e":6},{"0":3,"e":6},{"0":3,"e":6},{"0":3,"e":6},{"0":3,"e":6},{"0":3,"e":8},{"0":3,"e":9},{"0":3,"e":6},{"0":3,"e":6},{"0":3,"e":6},{"0":3,"e":6},{"0":3,"e":7},{"0":3,"e":8},{"0":3,"e":6},{"0":3,"e":6},{"0":2,"e":5},{"0":2,"e":4},{"0":2,"e":4},{"0":2,"e":4},{"0":2,"e":4},{"0":1,"e":2},{"0":1,"e":2}]}],"D":[{"0":3,"d":60,"E":[{"0":3,"e":15},{"0":3,"e":15},{"0":3,"e":16},{"0":3,"e":16},{"0":3,"e":19},{"0":3,"e":16},{"0":3,"e":16},{"0":3,"e":23},{"0":3,"e":12},{"0":3,"e":14},{"0":3,"e":22},{"0":3,"e":10},{"0":3,"e":20},{"0":3,"e":18},{"0":3,"e":13},{"0":3,"e":17},{"0":2,"e":16},{"0":2,"e":14},{"0":2,"e":10},{"0":2,"e":9},{"0":2,"e":11},{"0":1,"e":4},{"0":1,"e":5}]}]},{"0":3,"c":3,"C":[{"0":3,"d":3,"E":[{"0":3,"e":3}]}],"D":[{"0":3,"d":3,"E":[{"0":3,"e":3}]}]}]},{"0":3,"b":6,"B":[{"0":3,"c":3,"C":[{"0":3,"d":88,"E":[{"0":3,"e":12},{"0":3,"e":6},{"0":3,"e":8},{"0":3,"e":6},{"0":3,"e":6},{"0":3,"e":6},{"0":3,"e":7},{"0":3,"e":8},{"0":3,"e":6},{"0":3,"e":6},{"0":3,"e":6},{"0":3,"e":7},{"0":3,"e":6},{"0":3,"e":6},{"0":3,"e":6},{"0":3,"e":7},{"0":3,"e":7},{"0":3,"e":8},{"0":3,"e":6},{"0":3,"e":7},{"0":3,"e":6},{"0":2,"e":5},{"0":2,"e":4},{"0":2,"e":4},{"0":2,"e":4},{"0":2,"e":4},{"0":2,"e":5},{"0":2,"e":4},{"0":2,"e":4},{"0":1,"e":2},{"0":1,"e":2},{"0":1,"e":2},{"0":1,"e":3},{"0":1,"e":2},{"0":1,"e":2},{"0":1,"e":4},{"0":1,"e":2},{"0":1,"e":2}]}],"D":[{"0":3,"d":88,"E":[{"0":3,"e":15},{"0":3,"e":20},{"0":3,"e":15},{"0":3,"e":15},{"0":3,"e":21},{"0":3,"e":19},{"0":3,"e":20},{"0":3,"e":16},{"0":3,"e":16},{"0":3,"e":14},{"0":3,"e":20},{"0":3,"e":18},{"0":3,"e":12},{"0":3,"e":15},{"0":3,"e":16},{"0":3,"e":15},{"0":3,"e":19},{"0":3,"e":21},{"0":3,"e":20},{"0":3,"e":12},{"0":3,"e":17},{"0":2,"e":13},{"0":2,"e":8},{"0":2,"e":14},{"0":2,"e":7},{"0":2,"e":10},{"0":2,"e":11},{"0":2,"e":9},{"0":2,"e":13},{"0":1,"e":5},{"0":1,"e":9},{"0":1,"e":3},{"0":1,"e":5},{"0":1,"e":3},{"0":1,"e":4},{"0":1,"e":7},{"0":1,"e":10},{"0":1,"e":6}]}]},{"0":3,"c":3,"C":[{"0":3,"d":3,"E":[{"0":3,"e":3}]}],"D":[{"0":3,"d":3,"E":[{"0":3,"e":3}]}]}]},{"0":2,"b":4,"B":[{"0":2,"c":2,"C":[{"0":2,"d":64,"E":[{"0":2,"e":8},{"0":2,"e":4},{"0":2,"e":4},{"0":2,"e":4},{"0":2,"e":4},{"0":2,"e":4},{"0":2,"e":4},{"0":2,"e":4},{"0":2,"e":4},{"0":2,"e":4},{"0":2,"e":4},{"0":2,"e":4},{"0":2,"e":6},{"0":2,"e":4},{"0":2,"e":4},{"0":2,"e":4},{"0":2,"e":4},{"0":2,"e":4},{"0":2,"e":5},{"0":2,"e":4},{"0":2,"e":4},{"0":2,"e":7},{"0":2,"e":4},{"0":2,"e":4},{"0":2,"e":5},{"0":2,"e":4},{"0":2,"e":4},{"0":2,"e":4},{"0":1,"e":2},{"0":1,"e":2},{"0":1,"e":2},{"0":1,"e":2},{"0":1,"e":2},{"0":1,"e":2},{"0":1,"e":2},{"0":1,"e":2}]}],"D":[{"0":2,"d":64,"E":[{"0":2,"e":10},{"0":2,"e":6},{"0":2,"e":9},{"0":2,"e":14},{"0":2,"e":9},{"0":2,"e":9},{"0":2,"e":14},{"0":2,"e":12},{"0":2,"e":10},{"0":2,"e":9},{"0":2,"e":12},{"0":2,"e":7},{"0":2,"e":15},{"0":2,"e":5},{"0":2,"e":13},{"0":2,"e":12},{"0":2,"e":11},{"0":2,"e":10},{"0":2,"e":20},{"0":2,"e":9},{"0":2,"e":12},{"0":2,"e":17},{"0":2,"e":10},{"0":2,"e":8},{"0":2,"e":15},{"0":2,"e":7},{"0":2,"e":9},{"0":2,"e":15},{"0":1,"e":5},{"0":1,"e":3},{"0":1,"e":3},{"0":1,"e":6},{"0":1,"e":3},{"0":1,"e":4},{"0":1,"e":3},{"0":1,"e":7}]}]},{"0":2,"c":2,"C":[{"0":2,"d":2,"E":[{"0":2,"e":2}]}],"D":[{"0":2,"d":2,"E":[{"0":2,"e":2}]}]}]},{"0":2,"b":4,"B":[{"0":2,"c":2,"C":[{"0":2,"d":48,"E":[{"0":2,"e":8},{"0":2,"e":4},{"0":2,"e":4},{"0":2,"e":4},{"0":2,"e":4},{"0":2,"e":4},{"0":2,"e":4},{"0":2,"e":4},{"0":2,"e":4},{"0":2,"e":4},{"0":2,"e":4},{"0":2,"e":4},{"0":2,"e":4},{"0":2,"e":4},{"0":2,"e":4},{"0":2,"e":4},{"0":2,"e":5},{"0":2,"e":4},{"0":2,"e":4},{"0":1,"e":2},{"0":1,"e":2},{"0":1,"e":2},{"0":1,"e":2},{"0":1,"e":5},{"0":1,"e":2},{"0":1,"e":2},{"0":1,"e":4},{"0":1,"e":2},{"0":1,"e":2}]}],"D":[{"0":2,"d":48,"E":[{"0":2,"e":10},{"0":2,"e":9},{"0":2,"e":10},{"0":2,"e":10},{"0":2,"e":9},{"0":2,"e":11},{"0":2,"e":12},{"0":2,"e":10},{"0":2,"e":9},{"0":2,"e":13},{"0":2,"e":18},{"0":2,"e":9},{"0":2,"e":12},{"0":2,"e":13},{"0":2,"e":7},{"0":2,"e":9},{"0":2,"e":14},{"0":2,"e":14},{"0":2,"e":9},{"0":1,"e":4},{"0":1,"e":5},{"0":1,"e":3},{"0":1,"e":4},{"0":1,"e":8},{"0":1,"e":3},{"0":1,"e":4},{"0":1,"e":7},{"0":1,"e":10},{"0":1,"e":6}]}]},{"0":2,"c":2,"C":[{"0":2,"d":2,"E":[{"0":2,"e":2}]}],"D":[{"0":2,"d":2,"E":[{"0":2,"e":2}]}]}]},{"0":1,"b":2,"B":[{"0":1,"c":1,"C":[{"0":1,"d":16,"E":[{"0":1,"e":4},{"0":1,"e":2},{"0":1,"e":2},{"0":1,"e":2},{"0":1,"e":2},{"0":1,"e":2},{"0":1,"e":2},{"0":1,"e":2},{"0":1,"e":2},{"0":1,"e":2},{"0":1,"e":2},{"0":1,"e":2},{"0":1,"e":2},{"0":1,"e":2},{"0":1,"e":2},{"0":1,"e":2}]}],"D":[{"0":1,"d":16,"E":[{"0":1,"e":5},{"0":1,"e":2},{"0":1,"e":4},{"0":1,"e":4},{"0":1,"e":8},{"0":1,"e":6},{"0":1,"e":4},{"0":1,"e":6},{"0":1,"e":3},{"0":1,"e":6},{"0":1,"e":8},{"0":1,"e":5},{"0":1,"e":4},{"0":1,"e":9},{"0":1,"e":6},{"0":1,"e":5}]}]},{"0":1,"c":1,"C":[{"0":1,"d":1,"E":[{"0":1,"e":1}]}],"D":[{"0":1,"d":1,"E":[{"0":1,"e":1}]}]}]},{"0":1,"b":2,"B":[{"0":1,"c":1,"C":[{"0":1,"d":9,"E":[{"0":1,"e":4},{"0":1,"e":2},{"0":1,"e":2},{"0":1,"e":4},{"0":1,"e":2},{"0":1,"e":2},{"0":1,"e":2},{"0":1,"e":3},{"0":1,"e":2}]}],"D":[{"0":1,"d":9,"E":[{"0":1,"e":5},{"0":1,"e":4},{"0":1,"e":4},{"0":1,"e":7},{"0":1,"e":4},{"0":1,"e":7},{"0":1,"e":5},{"0":1,"e":7},{"0":1,"e":7}]}]},{"0":1,"c":1,"C":[{"0":1,"d":1,"E":[{"0":1,"e":1}]}],"D":[{"0":1,"d":1,"E":[{"0":1,"e":1}]}]}]},{"0":1,"b":2,"B":[{"0":1,"c":1,"C":[{"0":1,"d":21,"E":[{"0":1,"e":4},{"0":1,"e":2},{"0":1,"e":2},{"0":1,"e":2},{"0":1,"e":2},{"0":1,"e":2},{"0":1,"e":2},{"0":1,"e":2},{"0":1,"e":2},{"0":1,"e":3},{"0":1,"e":2},{"0":1,"e":2},{"0":1,"e":2},{"0":1,"e":2},{"0":1,"e":2},{"0":1,"e":2},{"0":1,"e":2},{"0":1,"e":2},{"0":1,"e":2},{"0":1,"e":2},{"0":1,"e":2}]}],"D":[{"0":1,"d":21,"E":[{"0":1,"e":5},{"0":1,"e":5},{"0":1,"e":5},{"0":1,"e":6},{"0":1,"e":4},{"0":1,"e":7},{"0":1,"e":4},{"0":1,"e":6},{"0":1,"e":3},{"0":1,"e":6},{"0":1,"e":8},{"0":1,"e":5},{"0":1,"e":4},{"0":1,"e":4},{"0":1,"e":3},{"0":1,"e":5},{"0":1,"e":6},{"0":1,"e":4},{"0":1,"e":9},{"0":1,"e":3},{"0":1,"e":7}]}]},{"0":1,"c":1,"C":[{"0":1,"d":1,"E":[{"0":1,"e":1}]}],"D":[{"0":1,"d":1,"E":[{"0":1,"e":1}]}]}]},{"0":1,"b":2,"B":[{"0":1,"c":1,"C":[{"0":1,"d":49,"E":[{"0":1,"e":4},{"0":1,"e":2},{"0":1,"e":2},{"0":1,"e":2},{"0":1,"e":2},{"0":1,"e":2},{"0":1,"e":2},{"0":1,"e":2},{"0":1,"e":2},{"0":1,"e":2},{"0":1,"e":2},{"0":1,"e":3},{"0":1,"e":2},{"0":1,"e":2},{"0":1,"e":2},{"0":1,"e":2},{"0":1,"e":2},{"0":1,"e":3},{"0":1,"e":2},{"0":1,"e":2},{"0":1,"e":2},{"0":1,"e":2},{"0":1,"e":2},{"0":1,"e":4},{"0":1,"e":2},{"0":1,"e":3},{"0":1,"e":2},{"0":1,"e":2},{"0":1,"e":2},{"0":1,"e":2},{"0":1,"e":3},{"0":1,"e":2},{"0":1,"e":2},{"0":1,"e":2},{"0":1,"e":2},{"0":1,"e":3},{"0":1,"e":2},{"0":1,"e":2},{"0":1,"e":2},{"0":1,"e":2},{"0":1,"e":2},{"0":1,"e":3},{"0":1,"e":2},{"0":1,"e":2},{"0":1,"e":2},{"0":1,"e":2},{"0":1,"e":2},{"0":1,"e":2},{"0":1,"e":2}]}],"D":[{"0":1,"d":49,"E":[{"0":1,"e":5},{"0":1,"e":4},{"0":1,"e":5},{"0":1,"e":6},{"0":1,"e":8},{"0":1,"e":4},{"0":1,"e":8},{"0":1,"e":5},{"0":1,"e":4},{"0":1,"e":11},{"0":1,"e":3},{"0":1,"e":11},{"0":1,"e":4},{"0":1,"e":5},{"0":1,"e":4},{"0":1,"e":4},{"0":1,"e":8},{"0":1,"e":9},{"0":1,"e":4},{"0":1,"e":5},{"0":1,"e":4},{"0":1,"e":7},{"0":1,"e":5},{"0":1,"e":9},{"0":1,"e":3},{"0":1,"e":4},{"0":1,"e":5},{"0":1,"e":6},{"0":1,"e":5},{"0":1,"e":4},{"0":1,"e":12},{"0":1,"e":4},{"0":1,"e":4},{"0":1,"e":4},{"0":1,"e":8},{"0":1,"e":9},{"0":1,"e":4},{"0":1,"e":5},{"0":1,"e":6},{"0":1,"e":9},{"0":1,"e":5},{"0":1,"e":4},{"0":1,"e":4},{"0":1,"e":6},{"0":1,"e":7},{"0":1,"e":6},{"0":1,"e":6},{"0":1,"e":4},{"0":1,"e":11}]}]},{"0":1,"c":1,"C":[{"0":1,"d":1,"E":[{"0":1,"e":1}]}],"D":[{"0":1,"d":1,"E":[{"0":1,"e":1}]}]}]},{"0":1,"b":2,"B":[{"0":1,"c":1,"C":[{"0":1,"d":38,"E":[{"0":1,"e":4},{"0":1,"e":2},{"0":1,"e":2},{"0":1,"e":2},{"0":1,"e":2},{"0":1,"e":2},{"0":1,"e":3},{"0":1,"e":2},{"0":1,"e":2},{"0":1,"e":2},{"0":1,"e":2},{"0":1,"e":2},{"0":1,"e":3},{"0":1,"e":2},{"0":1,"e":2},{"0":1,"e":2},{"0":1,"e":2},{"0":1,"e":2},{"0":1,"e":2},{"0":1,"e":2},{"0":1,"e":3},{"0":1,"e":2},{"0":1,"e":2},{"0":1,"e":2},{"0":1,"e":2},{"0":1,"e":2},{"0":1,"e":3},{"0":1,"e":2},{"0":1,"e":2},{"0":1,"e":2},{"0":1,"e":2},{"0":1,"e":2},{"0":1,"e":2},{"0":1,"e":2},{"0":1,"e":2},{"0":1,"e":2},{"0":1,"e":2},{"0":1,"e":2}]}],"D":[{"0":1,"d":38,"E":[{"0":1,"e":5},{"0":1,"e":4},{"0":1,"e":5},{"0":1,"e":4},{"0":1,"e":11},{"0":1,"e":8},{"0":1,"e":9},{"0":1,"e":4},{"0":1,"e":8},{"0":1,"e":6},{"0":1,"e":5},{"0":1,"e":3},{"0":1,"e":6},{"0":1,"e":4},{"0":1,"e":5},{"0":1,"e":4},{"0":1,"e":11},{"0":1,"e":3},{"0":1,"e":3},{"0":1,"e":3},{"0":1,"e":9},{"0":1,"e":4},{"0":1,"e":8},{"0":1,"e":6},{"0":1,"e":4},{"0":1,"e":3},{"0":1,"e":4},{"0":1,"e":4},{"0":1,"e":4},{"0":1,"e":9},{"0":1,"e":5},{"0":1,"e":7},{"0":1,"e":5},{"0":1,"e":6},{"0":1,"e":3},{"0":1,"e":4},{"0":1,"e":3},{"0":1,"e":6}]}]},{"0":1,"c":1,"C":[{"0":1,"d":1,"E":[{"0":1,"e":1}]}],"D":[{"0":1,"d":1,"E":[{"0":1,"e":1}]}]}]},{"0":1,"b":2,"B":[{"0":1,"c":1,"C":[{"0":1,"d":26,"E":[{"0":1,"e":4},{"0":1,"e":2},{"0":1,"e":2},{"0":1,"e":2},{"0":1,"e":2},{"0":1,"e":2},{"0":1,"e":2},{"0":1,"e":2},{"0":1,"e":2},{"0":1,"e":3},{"0":1,"e":2},{"0":1,"e":2},{"0":1,"e":2},{"0":1,"e":2},{"0":1,"e":2},{"0":1,"e":3},{"0":1,"e":2},{"0":1,"e":2},{"0":1,"e":2},{"0":1,"e":2},{"0":1,"e":2},{"0":1,"e":2},{"0":1,"e":3},{"0":1,"e":2},{"0":1,"e":2},{"0":1,"e":2}]}],"D":[{"0":1,"d":26,"E":[{"0":1,"e":5},{"0":1,"e":4},{"0":1,"e":4},{"0":1,"e":9},{"0":1,"e":3},{"0":1,"e":7},{"0":1,"e":6},{"0":1,"e":6},{"0":1,"e":6},{"0":1,"e":7},{"0":1,"e":6},{"0":1,"e":4},{"0":1,"e":3},{"0":1,"e":4},{"0":1,"e":4},{"0":1,"e":6},{"0":1,"e":4},{"0":1,"e":6},{"0":1,"e":4},{"0":1,"e":3},{"0":1,"e":4},{"0":1,"e":4},{"0":1,"e":10},{"0":1,"e":11},{"0":1,"e":6},{"0":1,"e":6}]}]},{"0":1,"c":1,"C":[{"0":1,"d":1,"E":[{"0":1,"e":1}]}],"D":[{"0":1,"d":1,"E":[{"0":1,"e":1}]}]}]},{"0":1,"b":2,"B":[{"0":1,"c":1,"C":[{"0":1,"d":37,"E":[{"0":1,"e":4},{"0":1,"e":2},{"0":1,"e":2},{"0":1,"e":2},{"0":1,"e":2},{"0":1,"e":2},{"0":1,"e":2},{"0":1,"e":2},{"0":1,"e":2},{"0":1,"e":2},{"0":1,"e":2},{"0":1,"e":3},{"0":1,"e":2},{"0":1,"e":2},{"0":1,"e":2},{"0":1,"e":2},{"0":1,"e":2},{"0":1,"e":2},{"0":1,"e":2},{"0":1,"e":2},{"0":1,"e":2},{"0":1,"e":2},{"0":1,"e":2},{"0":1,"e":2},{"0":1,"e":3},{"0":1,"e":2},{"0":1,"e":2},{"0":1,"e":2},{"0":1,"e":2},{"0":1,"e":2},{"0":1,"e":2},{"0":1,"e":2},{"0":1,"e":2},{"0":1,"e":2},{"0":1,"e":2},{"0":1,"e":2},{"0":1,"e":2}]}],"D":[{"0":1,"d":37,"E":[{"0":1,"e":5},{"0":1,"e":4},{"0":1,"e":4},{"0":1,"e":8},{"0":1,"e":6},{"0":1,"e":6},{"0":1,"e":6},{"0":1,"e":6},{"0":1,"e":4},{"0":1,"e":11},{"0":1,"e":3},{"0":1,"e":11},{"0":1,"e":5},{"0":1,"e":6},{"0":1,"e":3},{"0":1,"e":3},{"0":1,"e":6},{"0":1,"e":5},{"0":1,"e":4},{"0":1,"e":13},{"0":1,"e":3},{"0":1,"e":4},{"0":1,"e":9},{"0":1,"e":3},{"0":1,"e":8},{"0":1,"e":4},{"0":1,"e":4},{"0":1,"e":8},{"0":1,"e":6},{"0":1,"e":5},{"0":1,"e":4},{"0":1,"e":7},{"0":1,"e":3},{"0":1,"e":4},{"0":1,"e":11},{"0":1,"e":3},{"0":1,"e":10}]}]},{"0":1,"c":1,"C":[{"0":1,"d":1,"E":[{"0":1,"e":1}]}],"D":[{"0":1,"d":1,"E":[{"0":1,"e":1}]}]}]},{"0":1,"b":2,"B":[{"0":1,"c":1,"C":[{"0":1,"d":18,"E":[{"0":1,"e":4},{"0":1,"e":2},{"0":1,"e":2},{"0":1,"e":2},{"0":1,"e":2},{"0":1,"e":2},{"0":1,"e":2},{"0":1,"e":2},{"0":1,"e":2},{"0":1,"e":2},{"0":1,"e":2},{"0":1,"e":2},{"0":1,"e":4},{"0":1,"e":2},{"0":1,"e":3},{"0":1,"e":2},{"0":1,"e":2},{"0":1,"e":2}]}],"D":[{"0":1,"d":18,"E":[{"0":1,"e":5},{"0":1,"e":4},{"0":1,"e":4},{"0":1,"e":9},{"0":1,"e":3},{"0":1,"e":7},{"0":1,"e":4},{"0":1,"e":10},{"0":1,"e":3},{"0":1,"e":4},{"0":1,"e":5},{"0":1,"e":4},{"0":1,"e":7},{"0":1,"e":10},{"0":1,"e":7},{"0":1,"e":3},{"0":1,"e":4},{"0":1,"e":5}]}]},{"0":1,"c":1,"C":[{"0":1,"d":1,"E":[{"0":1,"e":1}]}],"D":[{"0":1,"d":1,"E":[{"0":1,"e":1}]}]}]}]}}